{
  "dataset": "arrowhead_1_vs_2",
  "dataset_metadata": {
    "n_instances": 130,
    "n_features": 249,
    "avg_binary_instance_size": 789.6,
    "avg_theory_clauses": 559.9
  },
  "experiment_config": {
    "n_folds": 10,
    "total_instances": 100,
    "instances_per_fold": 10
  },
  "methods": {
    "external_cooper_amgoud": {
      "mean_time_s": null,
      "timeout_count": 100,
      "timeout_percentage": 100.0,
      "mean_raw_size": null,
      "mean_feature_size": null,
      "success_count": 0
    },
    "pyxai_cpi_xp": {
      "mean_time_s": 0.3143400191701949,
      "timeout_count": 0,
      "timeout_percentage": 0.0,
      "mean_raw_size": 257.17,
      "mean_feature_size": 91.61,
      "success_count": 100
    },
    "pyxai_m_cpi_xp": {
      "mean_time_s": 0.39518085442250594,
      "timeout_count": 0,
      "timeout_percentage": 0.0,
      "mean_raw_size": 98.28,
      "mean_feature_size": 91.61,
      "success_count": 100
    },
    "pyxai_sufficient_reason": {
      "mean_time_s": null,
      "timeout_count": 100,
      "timeout_percentage": 100.0,
      "mean_raw_size": null,
      "mean_feature_size": null,
      "success_count": 0
    }
  },
  "detailed_results": [
    {
      "fold": 1,
      "instance_idx": 1,
      "prediction": 1,
      "len_binary_repr": 777,
      "len_theory": 549,
      "time_ext": 60.00126071507111,
      "status_ext": "Timeout",
      "len_raw_ext": null,
      "len_feat_ext": null,
      "time_cpi": 0.313873996026814,
      "status_cpi": "Success",
      "len_raw_cpi": 241,
      "len_feat_cpi": 92,
      "time_mcpi": 0.38403017609380186,
      "status_mcpi": "Success",
      "len_raw_mcpi": 97,
      "len_feat_mcpi": 92,
      "time_sr": 1.7227837815880775e-05,
      "status_sr": "Error: ExplainerRF.sufficient_reason() got an unexpected keyword argument 'n'",
      "len_raw_sr": null,
      "len_feat_sr": null
    },
    {
      "fold": 1,
      "instance_idx": 2,
      "prediction": 1,
      "len_binary_repr": 777,
      "len_theory": 549,
      "time_ext": 60.001910840161145,
      "status_ext": "Timeout",
      "len_raw_ext": null,
      "len_feat_ext": null,
      "time_cpi": 0.3903639428317547,
      "status_cpi": "Success",
      "len_raw_cpi": 291,
      "len_feat_cpi": 104,
      "time_mcpi": 0.38189054606482387,
      "status_mcpi": "Success",
      "len_raw_mcpi": 115,
      "len_feat_mcpi": 104,
      "time_sr": 1.6184058040380478e-05,
      "status_sr": "Error: ExplainerRF.sufficient_reason() got an unexpected keyword argument 'n'",
      "len_raw_sr": null,
      "len_feat_sr": null
    },
    {
      "fold": 1,
      "instance_idx": 3,
      "prediction": 1,
      "len_binary_repr": 777,
      "len_theory": 549,
      "time_ext": 60.001782342093065,
      "status_ext": "Timeout",
      "len_raw_ext": null,
      "len_feat_ext": null,
      "time_cpi": 0.4109182299580425,
      "status_cpi": "Success",
      "len_raw_cpi": 271,
      "len_feat_cpi": 88,
      "time_mcpi": 0.5227190770674497,
      "status_mcpi": "Success",
      "len_raw_mcpi": 89,
      "len_feat_mcpi": 88,
      "time_sr": 1.4526071026921272e-05,
      "status_sr": "Error: ExplainerRF.sufficient_reason() got an unexpected keyword argument 'n'",
      "len_raw_sr": null,
      "len_feat_sr": null
    },
    {
      "fold": 1,
      "instance_idx": 4,
      "prediction": 1,
      "len_binary_repr": 777,
      "len_theory": 549,
      "time_ext": 60.00161730707623,
      "status_ext": "Timeout",
      "len_raw_ext": null,
      "len_feat_ext": null,
      "time_cpi": 0.3379699110519141,
      "status_cpi": "Success",
      "len_raw_cpi": 280,
      "len_feat_cpi": 100,
      "time_mcpi": 0.4551195679232478,
      "status_mcpi": "Success",
      "len_raw_mcpi": 103,
      "len_feat_mcpi": 100,
      "time_sr": 1.512095332145691e-05,
      "status_sr": "Error: ExplainerRF.sufficient_reason() got an unexpected keyword argument 'n'",
      "len_raw_sr": null,
      "len_feat_sr": null
    },
    {
      "fold": 1,
      "instance_idx": 5,
      "prediction": 1,
      "len_binary_repr": 777,
      "len_theory": 549,
      "time_ext": 60.00139270606451,
      "status_ext": "Timeout",
      "len_raw_ext": null,
      "len_feat_ext": null,
      "time_cpi": 0.29918038682080805,
      "status_cpi": "Success",
      "len_raw_cpi": 246,
      "len_feat_cpi": 94,
      "time_mcpi": 0.37065882608294487,
      "status_mcpi": "Success",
      "len_raw_mcpi": 97,
      "len_feat_mcpi": 94,
      "time_sr": 1.2798001989722252e-05,
      "status_sr": "Error: ExplainerRF.sufficient_reason() got an unexpected keyword argument 'n'",
      "len_raw_sr": null,
      "len_feat_sr": null
    },
    {
      "fold": 1,
      "instance_idx": 6,
      "prediction": 1,
      "len_binary_repr": 777,
      "len_theory": 549,
      "time_ext": 60.001526192063466,
      "status_ext": "Timeout",
      "len_raw_ext": null,
      "len_feat_ext": null,
      "time_cpi": 0.3945078400429338,
      "status_cpi": "Success",
      "len_raw_cpi": 273,
      "len_feat_cpi": 99,
      "time_mcpi": 0.5105235821101815,
      "status_mcpi": "Success",
      "len_raw_mcpi": 106,
      "len_feat_mcpi": 99,
      "time_sr": 1.4796853065490723e-05,
      "status_sr": "Error: ExplainerRF.sufficient_reason() got an unexpected keyword argument 'n'",
      "len_raw_sr": null,
      "len_feat_sr": null
    },
    {
      "fold": 1,
      "instance_idx": 7,
      "prediction": 1,
      "len_binary_repr": 777,
      "len_theory": 549,
      "time_ext": 60.001523063052446,
      "status_ext": "Timeout",
      "len_raw_ext": null,
      "len_feat_ext": null,
      "time_cpi": 0.3104172549210489,
      "status_cpi": "Success",
      "len_raw_cpi": 246,
      "len_feat_cpi": 93,
      "time_mcpi": 0.39112826297059655,
      "status_mcpi": "Success",
      "len_raw_mcpi": 97,
      "len_feat_mcpi": 93,
      "time_sr": 1.2980075553059578e-05,
      "status_sr": "Error: ExplainerRF.sufficient_reason() got an unexpected keyword argument 'n'",
      "len_raw_sr": null,
      "len_feat_sr": null
    },
    {
      "fold": 1,
      "instance_idx": 8,
      "prediction": 0,
      "len_binary_repr": 777,
      "len_theory": 549,
      "time_ext": 60.00183219416067,
      "status_ext": "Timeout",
      "len_raw_ext": null,
      "len_feat_ext": null,
      "time_cpi": 0.30938211688771844,
      "status_cpi": "Success",
      "len_raw_cpi": 220,
      "len_feat_cpi": 73,
      "time_mcpi": 0.37649442395195365,
      "status_mcpi": "Success",
      "len_raw_mcpi": 80,
      "len_feat_mcpi": 73,
      "time_sr": 1.3463897630572319e-05,
      "status_sr": "Error: ExplainerRF.sufficient_reason() got an unexpected keyword argument 'n'",
      "len_raw_sr": null,
      "len_feat_sr": null
    },
    {
      "fold": 1,
      "instance_idx": 9,
      "prediction": 0,
      "len_binary_repr": 777,
      "len_theory": 549,
      "time_ext": 60.0019738660194,
      "status_ext": "Timeout",
      "len_raw_ext": null,
      "len_feat_ext": null,
      "time_cpi": 0.3118975639808923,
      "status_cpi": "Success",
      "len_raw_cpi": 238,
      "len_feat_cpi": 87,
      "time_mcpi": 0.38270198996178806,
      "status_mcpi": "Success",
      "len_raw_mcpi": 97,
      "len_feat_mcpi": 87,
      "time_sr": 1.38839241117239e-05,
      "status_sr": "Error: ExplainerRF.sufficient_reason() got an unexpected keyword argument 'n'",
      "len_raw_sr": null,
      "len_feat_sr": null
    },
    {
      "fold": 1,
      "instance_idx": 10,
      "prediction": 0,
      "len_binary_repr": 777,
      "len_theory": 549,
      "time_ext": 60.00158308306709,
      "status_ext": "Timeout",
      "len_raw_ext": null,
      "len_feat_ext": null,
      "time_cpi": 0.31619327096268535,
      "status_cpi": "Success",
      "len_raw_cpi": 294,
      "len_feat_cpi": 95,
      "time_mcpi": 0.42016170104034245,
      "status_mcpi": "Success",
      "len_raw_mcpi": 101,
      "len_feat_mcpi": 95,
      "time_sr": 1.3069016858935356e-05,
      "status_sr": "Error: ExplainerRF.sufficient_reason() got an unexpected keyword argument 'n'",
      "len_raw_sr": null,
      "len_feat_sr": null
    },
    {
      "fold": 2,
      "instance_idx": 1,
      "prediction": 1,
      "len_binary_repr": 802,
      "len_theory": 571,
      "time_ext": 60.00181729509495,
      "status_ext": "Timeout",
      "len_raw_ext": null,
      "len_feat_ext": null,
      "time_cpi": 0.3068592690397054,
      "status_cpi": "Success",
      "len_raw_cpi": 282,
      "len_feat_cpi": 95,
      "time_mcpi": 0.389017712790519,
      "status_mcpi": "Success",
      "len_raw_mcpi": 99,
      "len_feat_mcpi": 95,
      "time_sr": 1.2828968465328217e-05,
      "status_sr": "Error: ExplainerRF.sufficient_reason() got an unexpected keyword argument 'n'",
      "len_raw_sr": null,
      "len_feat_sr": null
    },
    {
      "fold": 2,
      "instance_idx": 2,
      "prediction": 1,
      "len_binary_repr": 802,
      "len_theory": 571,
      "time_ext": 60.00125234085135,
      "status_ext": "Timeout",
      "len_raw_ext": null,
      "len_feat_ext": null,
      "time_cpi": 0.1883634510450065,
      "status_cpi": "Success",
      "len_raw_cpi": 263,
      "len_feat_cpi": 101,
      "time_mcpi": 0.24395843618549407,
      "status_mcpi": "Success",
      "len_raw_mcpi": 107,
      "len_feat_mcpi": 101,
      "time_sr": 1.1100899428129196e-05,
      "status_sr": "Error: ExplainerRF.sufficient_reason() got an unexpected keyword argument 'n'",
      "len_raw_sr": null,
      "len_feat_sr": null
    },
    {
      "fold": 2,
      "instance_idx": 3,
      "prediction": 1,
      "len_binary_repr": 802,
      "len_theory": 571,
      "time_ext": 60.00115499389358,
      "status_ext": "Timeout",
      "len_raw_ext": null,
      "len_feat_ext": null,
      "time_cpi": 0.20152195892296731,
      "status_cpi": "Success",
      "len_raw_cpi": 243,
      "len_feat_cpi": 93,
      "time_mcpi": 0.2577702400740236,
      "status_mcpi": "Success",
      "len_raw_mcpi": 102,
      "len_feat_mcpi": 93,
      "time_sr": 1.008785329759121e-05,
      "status_sr": "Error: ExplainerRF.sufficient_reason() got an unexpected keyword argument 'n'",
      "len_raw_sr": null,
      "len_feat_sr": null
    },
    {
      "fold": 2,
      "instance_idx": 4,
      "prediction": 1,
      "len_binary_repr": 802,
      "len_theory": 571,
      "time_ext": 60.00193319097161,
      "status_ext": "Timeout",
      "len_raw_ext": null,
      "len_feat_ext": null,
      "time_cpi": 0.32504013599827886,
      "status_cpi": "Success",
      "len_raw_cpi": 271,
      "len_feat_cpi": 102,
      "time_mcpi": 0.41083818790502846,
      "status_mcpi": "Success",
      "len_raw_mcpi": 111,
      "len_feat_mcpi": 102,
      "time_sr": 1.4247139915823936e-05,
      "status_sr": "Error: ExplainerRF.sufficient_reason() got an unexpected keyword argument 'n'",
      "len_raw_sr": null,
      "len_feat_sr": null
    },
    {
      "fold": 2,
      "instance_idx": 5,
      "prediction": 1,
      "len_binary_repr": 802,
      "len_theory": 571,
      "time_ext": 60.00204851012677,
      "status_ext": "Timeout",
      "len_raw_ext": null,
      "len_feat_ext": null,
      "time_cpi": 0.3878306339029223,
      "status_cpi": "Success",
      "len_raw_cpi": 325,
      "len_feat_cpi": 104,
      "time_mcpi": 0.3923218669369817,
      "status_mcpi": "Success",
      "len_raw_mcpi": 114,
      "len_feat_mcpi": 104,
      "time_sr": 1.3959826901555061e-05,
      "status_sr": "Error: ExplainerRF.sufficient_reason() got an unexpected keyword argument 'n'",
      "len_raw_sr": null,
      "len_feat_sr": null
    },
    {
      "fold": 2,
      "instance_idx": 6,
      "prediction": 1,
      "len_binary_repr": 802,
      "len_theory": 571,
      "time_ext": 60.00177417998202,
      "status_ext": "Timeout",
      "len_raw_ext": null,
      "len_feat_ext": null,
      "time_cpi": 0.326616324018687,
      "status_cpi": "Success",
      "len_raw_cpi": 244,
      "len_feat_cpi": 95,
      "time_mcpi": 0.4231088769156486,
      "status_mcpi": "Success",
      "len_raw_mcpi": 100,
      "len_feat_mcpi": 95,
      "time_sr": 1.347600482404232e-05,
      "status_sr": "Error: ExplainerRF.sufficient_reason() got an unexpected keyword argument 'n'",
      "len_raw_sr": null,
      "len_feat_sr": null
    },
    {
      "fold": 2,
      "instance_idx": 7,
      "prediction": 1,
      "len_binary_repr": 802,
      "len_theory": 571,
      "time_ext": 60.001632953993976,
      "status_ext": "Timeout",
      "len_raw_ext": null,
      "len_feat_ext": null,
      "time_cpi": 0.32081255596131086,
      "status_cpi": "Success",
      "len_raw_cpi": 282,
      "len_feat_cpi": 103,
      "time_mcpi": 0.4068298419006169,
      "status_mcpi": "Success",
      "len_raw_mcpi": 110,
      "len_feat_mcpi": 103,
      "time_sr": 1.3418029993772507e-05,
      "status_sr": "Error: ExplainerRF.sufficient_reason() got an unexpected keyword argument 'n'",
      "len_raw_sr": null,
      "len_feat_sr": null
    },
    {
      "fold": 2,
      "instance_idx": 8,
      "prediction": 1,
      "len_binary_repr": 802,
      "len_theory": 571,
      "time_ext": 60.001352813094854,
      "status_ext": "Timeout",
      "len_raw_ext": null,
      "len_feat_ext": null,
      "time_cpi": 0.32156647788360715,
      "status_cpi": "Success",
      "len_raw_cpi": 213,
      "len_feat_cpi": 80,
      "time_mcpi": 0.38333336310461164,
      "status_mcpi": "Success",
      "len_raw_mcpi": 87,
      "len_feat_mcpi": 80,
      "time_sr": 1.3693934306502342e-05,
      "status_sr": "Error: ExplainerRF.sufficient_reason() got an unexpected keyword argument 'n'",
      "len_raw_sr": null,
      "len_feat_sr": null
    },
    {
      "fold": 2,
      "instance_idx": 9,
      "prediction": 0,
      "len_binary_repr": 802,
      "len_theory": 571,
      "time_ext": 60.00138603779487,
      "status_ext": "Timeout",
      "len_raw_ext": null,
      "len_feat_ext": null,
      "time_cpi": 0.31318894610740244,
      "status_cpi": "Success",
      "len_raw_cpi": 277,
      "len_feat_cpi": 93,
      "time_mcpi": 0.39513096516020596,
      "status_mcpi": "Success",
      "len_raw_mcpi": 102,
      "len_feat_mcpi": 93,
      "time_sr": 1.337914727628231e-05,
      "status_sr": "Error: ExplainerRF.sufficient_reason() got an unexpected keyword argument 'n'",
      "len_raw_sr": null,
      "len_feat_sr": null
    },
    {
      "fold": 2,
      "instance_idx": 10,
      "prediction": 0,
      "len_binary_repr": 802,
      "len_theory": 571,
      "time_ext": 60.001728443894535,
      "status_ext": "Timeout",
      "len_raw_ext": null,
      "len_feat_ext": null,
      "time_cpi": 0.3404911260586232,
      "status_cpi": "Success",
      "len_raw_cpi": 259,
      "len_feat_cpi": 88,
      "time_mcpi": 0.42623595311306417,
      "status_mcpi": "Success",
      "len_raw_mcpi": 97,
      "len_feat_mcpi": 88,
      "time_sr": 1.2326054275035858e-05,
      "status_sr": "Error: ExplainerRF.sufficient_reason() got an unexpected keyword argument 'n'",
      "len_raw_sr": null,
      "len_feat_sr": null
    },
    {
      "fold": 3,
      "instance_idx": 1,
      "prediction": 1,
      "len_binary_repr": 806,
      "len_theory": 574,
      "time_ext": 60.00160483107902,
      "status_ext": "Timeout",
      "len_raw_ext": null,
      "len_feat_ext": null,
      "time_cpi": 0.35315845790319145,
      "status_cpi": "Success",
      "len_raw_cpi": 275,
      "len_feat_cpi": 99,
      "time_mcpi": 0.4654594329185784,
      "status_mcpi": "Success",
      "len_raw_mcpi": 105,
      "len_feat_mcpi": 99,
      "time_sr": 1.3659009709954262e-05,
      "status_sr": "Error: ExplainerRF.sufficient_reason() got an unexpected keyword argument 'n'",
      "len_raw_sr": null,
      "len_feat_sr": null
    },
    {
      "fold": 3,
      "instance_idx": 2,
      "prediction": 1,
      "len_binary_repr": 806,
      "len_theory": 574,
      "time_ext": 60.00172157189809,
      "status_ext": "Timeout",
      "len_raw_ext": null,
      "len_feat_ext": null,
      "time_cpi": 0.31084279203787446,
      "status_cpi": "Success",
      "len_raw_cpi": 237,
      "len_feat_cpi": 84,
      "time_mcpi": 0.37973733502440155,
      "status_mcpi": "Success",
      "len_raw_mcpi": 89,
      "len_feat_mcpi": 84,
      "time_sr": 1.4652032405138016e-05,
      "status_sr": "Error: ExplainerRF.sufficient_reason() got an unexpected keyword argument 'n'",
      "len_raw_sr": null,
      "len_feat_sr": null
    },
    {
      "fold": 3,
      "instance_idx": 3,
      "prediction": 1,
      "len_binary_repr": 806,
      "len_theory": 574,
      "time_ext": 60.00153892301023,
      "status_ext": "Timeout",
      "len_raw_ext": null,
      "len_feat_ext": null,
      "time_cpi": 0.31523700593970716,
      "status_cpi": "Success",
      "len_raw_cpi": 309,
      "len_feat_cpi": 106,
      "time_mcpi": 0.40076720085926354,
      "status_mcpi": "Success",
      "len_raw_mcpi": 121,
      "len_feat_mcpi": 106,
      "time_sr": 1.3424782082438469e-05,
      "status_sr": "Error: ExplainerRF.sufficient_reason() got an unexpected keyword argument 'n'",
      "len_raw_sr": null,
      "len_feat_sr": null
    },
    {
      "fold": 3,
      "instance_idx": 4,
      "prediction": 1,
      "len_binary_repr": 806,
      "len_theory": 574,
      "time_ext": 60.00171456998214,
      "status_ext": "Timeout",
      "len_raw_ext": null,
      "len_feat_ext": null,
      "time_cpi": 0.318675619084388,
      "status_cpi": "Success",
      "len_raw_cpi": 277,
      "len_feat_cpi": 103,
      "time_mcpi": 0.40254921396262944,
      "status_mcpi": "Success",
      "len_raw_mcpi": 111,
      "len_feat_mcpi": 103,
      "time_sr": 1.2808013707399368e-05,
      "status_sr": "Error: ExplainerRF.sufficient_reason() got an unexpected keyword argument 'n'",
      "len_raw_sr": null,
      "len_feat_sr": null
    },
    {
      "fold": 3,
      "instance_idx": 5,
      "prediction": 0,
      "len_binary_repr": 806,
      "len_theory": 574,
      "time_ext": 60.001714223995805,
      "status_ext": "Timeout",
      "len_raw_ext": null,
      "len_feat_ext": null,
      "time_cpi": 0.3262002649717033,
      "status_cpi": "Success",
      "len_raw_cpi": 230,
      "len_feat_cpi": 79,
      "time_mcpi": 0.4056073660030961,
      "status_mcpi": "Success",
      "len_raw_mcpi": 84,
      "len_feat_mcpi": 79,
      "time_sr": 1.3225013390183449e-05,
      "status_sr": "Error: ExplainerRF.sufficient_reason() got an unexpected keyword argument 'n'",
      "len_raw_sr": null,
      "len_feat_sr": null
    },
    {
      "fold": 3,
      "instance_idx": 6,
      "prediction": 0,
      "len_binary_repr": 806,
      "len_theory": 574,
      "time_ext": 60.00151156494394,
      "status_ext": "Timeout",
      "len_raw_ext": null,
      "len_feat_ext": null,
      "time_cpi": 0.34140719077549875,
      "status_cpi": "Success",
      "len_raw_cpi": 214,
      "len_feat_cpi": 73,
      "time_mcpi": 0.4252459569834173,
      "status_mcpi": "Success",
      "len_raw_mcpi": 74,
      "len_feat_mcpi": 73,
      "time_sr": 1.368718221783638e-05,
      "status_sr": "Error: ExplainerRF.sufficient_reason() got an unexpected keyword argument 'n'",
      "len_raw_sr": null,
      "len_feat_sr": null
    },
    {
      "fold": 3,
      "instance_idx": 7,
      "prediction": 0,
      "len_binary_repr": 806,
      "len_theory": 574,
      "time_ext": 60.00149849499576,
      "status_ext": "Timeout",
      "len_raw_ext": null,
      "len_feat_ext": null,
      "time_cpi": 0.40683562704361975,
      "status_cpi": "Success",
      "len_raw_cpi": 220,
      "len_feat_cpi": 75,
      "time_mcpi": 0.3997136689722538,
      "status_mcpi": "Success",
      "len_raw_mcpi": 78,
      "len_feat_mcpi": 75,
      "time_sr": 1.223594881594181e-05,
      "status_sr": "Error: ExplainerRF.sufficient_reason() got an unexpected keyword argument 'n'",
      "len_raw_sr": null,
      "len_feat_sr": null
    },
    {
      "fold": 3,
      "instance_idx": 8,
      "prediction": 0,
      "len_binary_repr": 806,
      "len_theory": 574,
      "time_ext": 60.00152134615928,
      "status_ext": "Timeout",
      "len_raw_ext": null,
      "len_feat_ext": null,
      "time_cpi": 0.3432841419707984,
      "status_cpi": "Success",
      "len_raw_cpi": 244,
      "len_feat_cpi": 100,
      "time_mcpi": 0.4298715000040829,
      "status_mcpi": "Success",
      "len_raw_mcpi": 104,
      "len_feat_mcpi": 100,
      "time_sr": 1.3981014490127563e-05,
      "status_sr": "Error: ExplainerRF.sufficient_reason() got an unexpected keyword argument 'n'",
      "len_raw_sr": null,
      "len_feat_sr": null
    },
    {
      "fold": 3,
      "instance_idx": 9,
      "prediction": 0,
      "len_binary_repr": 806,
      "len_theory": 574,
      "time_ext": 60.00143074686639,
      "status_ext": "Timeout",
      "len_raw_ext": null,
      "len_feat_ext": null,
      "time_cpi": 0.3949237600900233,
      "status_cpi": "Success",
      "len_raw_cpi": 254,
      "len_feat_cpi": 111,
      "time_mcpi": 0.49762361007742584,
      "status_mcpi": "Success",
      "len_raw_mcpi": 121,
      "len_feat_mcpi": 111,
      "time_sr": 1.3410812243819237e-05,
      "status_sr": "Error: ExplainerRF.sufficient_reason() got an unexpected keyword argument 'n'",
      "len_raw_sr": null,
      "len_feat_sr": null
    },
    {
      "fold": 3,
      "instance_idx": 10,
      "prediction": 0,
      "len_binary_repr": 806,
      "len_theory": 574,
      "time_ext": 60.00168472900987,
      "status_ext": "Timeout",
      "len_raw_ext": null,
      "len_feat_ext": null,
      "time_cpi": 0.3362733230460435,
      "status_cpi": "Success",
      "len_raw_cpi": 218,
      "len_feat_cpi": 83,
      "time_mcpi": 0.42468770197592676,
      "status_mcpi": "Success",
      "len_raw_mcpi": 86,
      "len_feat_mcpi": 83,
      "time_sr": 1.2318836525082588e-05,
      "status_sr": "Error: ExplainerRF.sufficient_reason() got an unexpected keyword argument 'n'",
      "len_raw_sr": null,
      "len_feat_sr": null
    },
    {
      "fold": 4,
      "instance_idx": 1,
      "prediction": 1,
      "len_binary_repr": 773,
      "len_theory": 547,
      "time_ext": 60.001967548858374,
      "status_ext": "Timeout",
      "len_raw_ext": null,
      "len_feat_ext": null,
      "time_cpi": 0.2972111178096384,
      "status_cpi": "Success",
      "len_raw_cpi": 255,
      "len_feat_cpi": 94,
      "time_mcpi": 0.3711880010087043,
      "status_mcpi": "Success",
      "len_raw_mcpi": 98,
      "len_feat_mcpi": 94,
      "time_sr": 1.3181939721107483e-05,
      "status_sr": "Error: ExplainerRF.sufficient_reason() got an unexpected keyword argument 'n'",
      "len_raw_sr": null,
      "len_feat_sr": null
    },
    {
      "fold": 4,
      "instance_idx": 2,
      "prediction": 1,
      "len_binary_repr": 773,
      "len_theory": 547,
      "time_ext": 60.00120605202392,
      "status_ext": "Timeout",
      "len_raw_ext": null,
      "len_feat_ext": null,
      "time_cpi": 0.29821360600180924,
      "status_cpi": "Success",
      "len_raw_cpi": 237,
      "len_feat_cpi": 79,
      "time_mcpi": 0.3733532738406211,
      "status_mcpi": "Success",
      "len_raw_mcpi": 86,
      "len_feat_mcpi": 79,
      "time_sr": 1.5127938240766525e-05,
      "status_sr": "Error: ExplainerRF.sufficient_reason() got an unexpected keyword argument 'n'",
      "len_raw_sr": null,
      "len_feat_sr": null
    },
    {
      "fold": 4,
      "instance_idx": 3,
      "prediction": 1,
      "len_binary_repr": 773,
      "len_theory": 547,
      "time_ext": 60.00186763401143,
      "status_ext": "Timeout",
      "len_raw_ext": null,
      "len_feat_ext": null,
      "time_cpi": 0.30014105793088675,
      "status_cpi": "Success",
      "len_raw_cpi": 263,
      "len_feat_cpi": 89,
      "time_mcpi": 0.37496185302734375,
      "status_mcpi": "Success",
      "len_raw_mcpi": 95,
      "len_feat_mcpi": 89,
      "time_sr": 1.309695653617382e-05,
      "status_sr": "Error: ExplainerRF.sufficient_reason() got an unexpected keyword argument 'n'",
      "len_raw_sr": null,
      "len_feat_sr": null
    },
    {
      "fold": 4,
      "instance_idx": 4,
      "prediction": 1,
      "len_binary_repr": 773,
      "len_theory": 547,
      "time_ext": 60.00160201312974,
      "status_ext": "Timeout",
      "len_raw_ext": null,
      "len_feat_ext": null,
      "time_cpi": 0.2981670559383929,
      "status_cpi": "Success",
      "len_raw_cpi": 236,
      "len_feat_cpi": 83,
      "time_mcpi": 0.37168672191910446,
      "status_mcpi": "Success",
      "len_raw_mcpi": 91,
      "len_feat_mcpi": 83,
      "time_sr": 1.4662044122815132e-05,
      "status_sr": "Error: ExplainerRF.sufficient_reason() got an unexpected keyword argument 'n'",
      "len_raw_sr": null,
      "len_feat_sr": null
    },
    {
      "fold": 4,
      "instance_idx": 5,
      "prediction": 0,
      "len_binary_repr": 773,
      "len_theory": 547,
      "time_ext": 60.00157707091421,
      "status_ext": "Timeout",
      "len_raw_ext": null,
      "len_feat_ext": null,
      "time_cpi": 0.3225660289172083,
      "status_cpi": "Success",
      "len_raw_cpi": 225,
      "len_feat_cpi": 85,
      "time_mcpi": 0.40029050107114017,
      "status_mcpi": "Success",
      "len_raw_mcpi": 92,
      "len_feat_mcpi": 85,
      "time_sr": 1.343083567917347e-05,
      "status_sr": "Error: ExplainerRF.sufficient_reason() got an unexpected keyword argument 'n'",
      "len_raw_sr": null,
      "len_feat_sr": null
    },
    {
      "fold": 4,
      "instance_idx": 6,
      "prediction": 0,
      "len_binary_repr": 773,
      "len_theory": 547,
      "time_ext": 60.00093295099214,
      "status_ext": "Timeout",
      "len_raw_ext": null,
      "len_feat_ext": null,
      "time_cpi": 0.1869581879582256,
      "status_cpi": "Success",
      "len_raw_cpi": 232,
      "len_feat_cpi": 87,
      "time_mcpi": 0.2340683350339532,
      "status_mcpi": "Success",
      "len_raw_mcpi": 94,
      "len_feat_mcpi": 87,
      "time_sr": 1.0052230209112167e-05,
      "status_sr": "Error: ExplainerRF.sufficient_reason() got an unexpected keyword argument 'n'",
      "len_raw_sr": null,
      "len_feat_sr": null
    },
    {
      "fold": 4,
      "instance_idx": 7,
      "prediction": 0,
      "len_binary_repr": 773,
      "len_theory": 547,
      "time_ext": 60.00127071002498,
      "status_ext": "Timeout",
      "len_raw_ext": null,
      "len_feat_ext": null,
      "time_cpi": 0.1885439120233059,
      "status_cpi": "Success",
      "len_raw_cpi": 218,
      "len_feat_cpi": 75,
      "time_mcpi": 0.2337511859368533,
      "status_mcpi": "Success",
      "len_raw_mcpi": 80,
      "len_feat_mcpi": 75,
      "time_sr": 9.045004844665527e-06,
      "status_sr": "Error: ExplainerRF.sufficient_reason() got an unexpected keyword argument 'n'",
      "len_raw_sr": null,
      "len_feat_sr": null
    },
    {
      "fold": 4,
      "instance_idx": 8,
      "prediction": 0,
      "len_binary_repr": 773,
      "len_theory": 547,
      "time_ext": 60.00130317104049,
      "status_ext": "Timeout",
      "len_raw_ext": null,
      "len_feat_ext": null,
      "time_cpi": 0.24193928902968764,
      "status_cpi": "Success",
      "len_raw_cpi": 221,
      "len_feat_cpi": 79,
      "time_mcpi": 0.22760588699020445,
      "status_mcpi": "Success",
      "len_raw_mcpi": 84,
      "len_feat_mcpi": 79,
      "time_sr": 1.0401010513305664e-05,
      "status_sr": "Error: ExplainerRF.sufficient_reason() got an unexpected keyword argument 'n'",
      "len_raw_sr": null,
      "len_feat_sr": null
    },
    {
      "fold": 4,
      "instance_idx": 9,
      "prediction": 0,
      "len_binary_repr": 773,
      "len_theory": 547,
      "time_ext": 60.001732209930196,
      "status_ext": "Timeout",
      "len_raw_ext": null,
      "len_feat_ext": null,
      "time_cpi": 0.31646784604527056,
      "status_cpi": "Success",
      "len_raw_cpi": 226,
      "len_feat_cpi": 85,
      "time_mcpi": 0.38986151618883014,
      "status_mcpi": "Success",
      "len_raw_mcpi": 89,
      "len_feat_mcpi": 85,
      "time_sr": 1.203198917210102e-05,
      "status_sr": "Error: ExplainerRF.sufficient_reason() got an unexpected keyword argument 'n'",
      "len_raw_sr": null,
      "len_feat_sr": null
    },
    {
      "fold": 4,
      "instance_idx": 10,
      "prediction": 0,
      "len_binary_repr": 773,
      "len_theory": 547,
      "time_ext": 60.0013881130144,
      "status_ext": "Timeout",
      "len_raw_ext": null,
      "len_feat_ext": null,
      "time_cpi": 0.3030515010468662,
      "status_cpi": "Success",
      "len_raw_cpi": 260,
      "len_feat_cpi": 105,
      "time_mcpi": 0.38735172199085355,
      "status_mcpi": "Success",
      "len_raw_mcpi": 114,
      "len_feat_mcpi": 105,
      "time_sr": 1.3081124052405357e-05,
      "status_sr": "Error: ExplainerRF.sufficient_reason() got an unexpected keyword argument 'n'",
      "len_raw_sr": null,
      "len_feat_sr": null
    },
    {
      "fold": 5,
      "instance_idx": 1,
      "prediction": 1,
      "len_binary_repr": 750,
      "len_theory": 520,
      "time_ext": 60.00151012511924,
      "status_ext": "Timeout",
      "len_raw_ext": null,
      "len_feat_ext": null,
      "time_cpi": 0.2973179218824953,
      "status_cpi": "Success",
      "len_raw_cpi": 219,
      "len_feat_cpi": 83,
      "time_mcpi": 0.3660449809394777,
      "status_mcpi": "Success",
      "len_raw_mcpi": 86,
      "len_feat_mcpi": 83,
      "time_sr": 1.599895767867565e-05,
      "status_sr": "Error: ExplainerRF.sufficient_reason() got an unexpected keyword argument 'n'",
      "len_raw_sr": null,
      "len_feat_sr": null
    },
    {
      "fold": 5,
      "instance_idx": 2,
      "prediction": 1,
      "len_binary_repr": 750,
      "len_theory": 520,
      "time_ext": 60.00154642108828,
      "status_ext": "Timeout",
      "len_raw_ext": null,
      "len_feat_ext": null,
      "time_cpi": 0.17820113711059093,
      "status_cpi": "Success",
      "len_raw_cpi": 219,
      "len_feat_cpi": 77,
      "time_mcpi": 0.22719267499633133,
      "status_mcpi": "Success",
      "len_raw_mcpi": 81,
      "len_feat_mcpi": 77,
      "time_sr": 2.5725923478603363e-05,
      "status_sr": "Error: ExplainerRF.sufficient_reason() got an unexpected keyword argument 'n'",
      "len_raw_sr": null,
      "len_feat_sr": null
    },
    {
      "fold": 5,
      "instance_idx": 3,
      "prediction": 1,
      "len_binary_repr": 750,
      "len_theory": 520,
      "time_ext": 60.00128805893473,
      "status_ext": "Timeout",
      "len_raw_ext": null,
      "len_feat_ext": null,
      "time_cpi": 0.18436065199784935,
      "status_cpi": "Success",
      "len_raw_cpi": 282,
      "len_feat_cpi": 104,
      "time_mcpi": 0.24266426800750196,
      "status_mcpi": "Success",
      "len_raw_mcpi": 108,
      "len_feat_mcpi": 104,
      "time_sr": 1.030205748975277e-05,
      "status_sr": "Error: ExplainerRF.sufficient_reason() got an unexpected keyword argument 'n'",
      "len_raw_sr": null,
      "len_feat_sr": null
    },
    {
      "fold": 5,
      "instance_idx": 4,
      "prediction": 1,
      "len_binary_repr": 750,
      "len_theory": 520,
      "time_ext": 60.001135538099334,
      "status_ext": "Timeout",
      "len_raw_ext": null,
      "len_feat_ext": null,
      "time_cpi": 0.17888098792172968,
      "status_cpi": "Success",
      "len_raw_cpi": 251,
      "len_feat_cpi": 96,
      "time_mcpi": 0.2284131192136556,
      "status_mcpi": "Success",
      "len_raw_mcpi": 108,
      "len_feat_mcpi": 96,
      "time_sr": 1.0005198419094086e-05,
      "status_sr": "Error: ExplainerRF.sufficient_reason() got an unexpected keyword argument 'n'",
      "len_raw_sr": null,
      "len_feat_sr": null
    },
    {
      "fold": 5,
      "instance_idx": 5,
      "prediction": 1,
      "len_binary_repr": 750,
      "len_theory": 520,
      "time_ext": 60.00106799486093,
      "status_ext": "Timeout",
      "len_raw_ext": null,
      "len_feat_ext": null,
      "time_cpi": 0.16707595600746572,
      "status_cpi": "Success",
      "len_raw_cpi": 243,
      "len_feat_cpi": 76,
      "time_mcpi": 0.20785926701501012,
      "status_mcpi": "Success",
      "len_raw_mcpi": 78,
      "len_feat_mcpi": 76,
      "time_sr": 8.439179509878159e-06,
      "status_sr": "Error: ExplainerRF.sufficient_reason() got an unexpected keyword argument 'n'",
      "len_raw_sr": null,
      "len_feat_sr": null
    },
    {
      "fold": 5,
      "instance_idx": 6,
      "prediction": 0,
      "len_binary_repr": 750,
      "len_theory": 520,
      "time_ext": 60.00163071998395,
      "status_ext": "Timeout",
      "len_raw_ext": null,
      "len_feat_ext": null,
      "time_cpi": 0.17224741983227432,
      "status_cpi": "Success",
      "len_raw_cpi": 205,
      "len_feat_cpi": 62,
      "time_mcpi": 0.21339100506156683,
      "status_mcpi": "Success",
      "len_raw_mcpi": 68,
      "len_feat_mcpi": 62,
      "time_sr": 1.0967021808028221e-05,
      "status_sr": "Error: ExplainerRF.sufficient_reason() got an unexpected keyword argument 'n'",
      "len_raw_sr": null,
      "len_feat_sr": null
    },
    {
      "fold": 5,
      "instance_idx": 7,
      "prediction": 0,
      "len_binary_repr": 750,
      "len_theory": 520,
      "time_ext": 60.00145598500967,
      "status_ext": "Timeout",
      "len_raw_ext": null,
      "len_feat_ext": null,
      "time_cpi": 0.18115298706106842,
      "status_cpi": "Success",
      "len_raw_cpi": 265,
      "len_feat_cpi": 106,
      "time_mcpi": 0.23780273995362222,
      "status_mcpi": "Success",
      "len_raw_mcpi": 116,
      "len_feat_mcpi": 106,
      "time_sr": 1.0838964954018593e-05,
      "status_sr": "Error: ExplainerRF.sufficient_reason() got an unexpected keyword argument 'n'",
      "len_raw_sr": null,
      "len_feat_sr": null
    },
    {
      "fold": 5,
      "instance_idx": 8,
      "prediction": 0,
      "len_binary_repr": 750,
      "len_theory": 520,
      "time_ext": 60.0011661129538,
      "status_ext": "Timeout",
      "len_raw_ext": null,
      "len_feat_ext": null,
      "time_cpi": 0.17439851397648454,
      "status_cpi": "Success",
      "len_raw_cpi": 248,
      "len_feat_cpi": 102,
      "time_mcpi": 0.22247055103071034,
      "status_mcpi": "Success",
      "len_raw_mcpi": 110,
      "len_feat_mcpi": 102,
      "time_sr": 9.95793379843235e-06,
      "status_sr": "Error: ExplainerRF.sufficient_reason() got an unexpected keyword argument 'n'",
      "len_raw_sr": null,
      "len_feat_sr": null
    },
    {
      "fold": 5,
      "instance_idx": 9,
      "prediction": 0,
      "len_binary_repr": 750,
      "len_theory": 520,
      "time_ext": 60.000867425929755,
      "status_ext": "Timeout",
      "len_raw_ext": null,
      "len_feat_ext": null,
      "time_cpi": 0.16808901983313262,
      "status_cpi": "Success",
      "len_raw_cpi": 226,
      "len_feat_cpi": 81,
      "time_mcpi": 0.21613450185395777,
      "status_mcpi": "Success",
      "len_raw_mcpi": 89,
      "len_feat_mcpi": 81,
      "time_sr": 8.600996807217598e-06,
      "status_sr": "Error: ExplainerRF.sufficient_reason() got an unexpected keyword argument 'n'",
      "len_raw_sr": null,
      "len_feat_sr": null
    },
    {
      "fold": 5,
      "instance_idx": 10,
      "prediction": 0,
      "len_binary_repr": 750,
      "len_theory": 520,
      "time_ext": 60.001086508855224,
      "status_ext": "Timeout",
      "len_raw_ext": null,
      "len_feat_ext": null,
      "time_cpi": 0.17320388602092862,
      "status_cpi": "Success",
      "len_raw_cpi": 258,
      "len_feat_cpi": 96,
      "time_mcpi": 0.22062749601900578,
      "status_mcpi": "Success",
      "len_raw_mcpi": 104,
      "len_feat_mcpi": 96,
      "time_sr": 9.190058335661888e-06,
      "status_sr": "Error: ExplainerRF.sufficient_reason() got an unexpected keyword argument 'n'",
      "len_raw_sr": null,
      "len_feat_sr": null
    },
    {
      "fold": 6,
      "instance_idx": 1,
      "prediction": 1,
      "len_binary_repr": 774,
      "len_theory": 549,
      "time_ext": 60.00156628806144,
      "status_ext": "Timeout",
      "len_raw_ext": null,
      "len_feat_ext": null,
      "time_cpi": 0.1749022190924734,
      "status_cpi": "Success",
      "len_raw_cpi": 239,
      "len_feat_cpi": 85,
      "time_mcpi": 0.22025024890899658,
      "status_mcpi": "Success",
      "len_raw_mcpi": 90,
      "len_feat_mcpi": 85,
      "time_sr": 1.2487871572375298e-05,
      "status_sr": "Error: ExplainerRF.sufficient_reason() got an unexpected keyword argument 'n'",
      "len_raw_sr": null,
      "len_feat_sr": null
    },
    {
      "fold": 6,
      "instance_idx": 2,
      "prediction": 1,
      "len_binary_repr": 774,
      "len_theory": 549,
      "time_ext": 60.00160988001153,
      "status_ext": "Timeout",
      "len_raw_ext": null,
      "len_feat_ext": null,
      "time_cpi": 0.29017471289262176,
      "status_cpi": "Success",
      "len_raw_cpi": 234,
      "len_feat_cpi": 88,
      "time_mcpi": 0.4406246431171894,
      "status_mcpi": "Success",
      "len_raw_mcpi": 91,
      "len_feat_mcpi": 88,
      "time_sr": 1.2950971722602844e-05,
      "status_sr": "Error: ExplainerRF.sufficient_reason() got an unexpected keyword argument 'n'",
      "len_raw_sr": null,
      "len_feat_sr": null
    },
    {
      "fold": 6,
      "instance_idx": 3,
      "prediction": 1,
      "len_binary_repr": 774,
      "len_theory": 549,
      "time_ext": 60.001634052954614,
      "status_ext": "Timeout",
      "len_raw_ext": null,
      "len_feat_ext": null,
      "time_cpi": 0.2977236839942634,
      "status_cpi": "Success",
      "len_raw_cpi": 233,
      "len_feat_cpi": 82,
      "time_mcpi": 0.3672970640473068,
      "status_mcpi": "Success",
      "len_raw_mcpi": 85,
      "len_feat_mcpi": 82,
      "time_sr": 1.326482743024826e-05,
      "status_sr": "Error: ExplainerRF.sufficient_reason() got an unexpected keyword argument 'n'",
      "len_raw_sr": null,
      "len_feat_sr": null
    },
    {
      "fold": 6,
      "instance_idx": 4,
      "prediction": 1,
      "len_binary_repr": 774,
      "len_theory": 549,
      "time_ext": 60.00193772884086,
      "status_ext": "Timeout",
      "len_raw_ext": null,
      "len_feat_ext": null,
      "time_cpi": 0.3134881758596748,
      "status_cpi": "Success",
      "len_raw_cpi": 236,
      "len_feat_cpi": 78,
      "time_mcpi": 0.3838686349336058,
      "status_mcpi": "Success",
      "len_raw_mcpi": 82,
      "len_feat_mcpi": 78,
      "time_sr": 1.2852950021624565e-05,
      "status_sr": "Error: ExplainerRF.sufficient_reason() got an unexpected keyword argument 'n'",
      "len_raw_sr": null,
      "len_feat_sr": null
    },
    {
      "fold": 6,
      "instance_idx": 5,
      "prediction": 1,
      "len_binary_repr": 774,
      "len_theory": 549,
      "time_ext": 60.00133061315864,
      "status_ext": "Timeout",
      "len_raw_ext": null,
      "len_feat_ext": null,
      "time_cpi": 0.17285181093029678,
      "status_cpi": "Success",
      "len_raw_cpi": 273,
      "len_feat_cpi": 87,
      "time_mcpi": 0.22459361306391656,
      "status_mcpi": "Success",
      "len_raw_mcpi": 90,
      "len_feat_mcpi": 87,
      "time_sr": 1.0435935109853745e-05,
      "status_sr": "Error: ExplainerRF.sufficient_reason() got an unexpected keyword argument 'n'",
      "len_raw_sr": null,
      "len_feat_sr": null
    },
    {
      "fold": 6,
      "instance_idx": 6,
      "prediction": 1,
      "len_binary_repr": 774,
      "len_theory": 549,
      "time_ext": 60.00140889501199,
      "status_ext": "Timeout",
      "len_raw_ext": null,
      "len_feat_ext": null,
      "time_cpi": 0.21995807089842856,
      "status_cpi": "Success",
      "len_raw_cpi": 212,
      "len_feat_cpi": 77,
      "time_mcpi": 0.2710371701978147,
      "status_mcpi": "Success",
      "len_raw_mcpi": 78,
      "len_feat_mcpi": 77,
      "time_sr": 8.782139047980309e-06,
      "status_sr": "Error: ExplainerRF.sufficient_reason() got an unexpected keyword argument 'n'",
      "len_raw_sr": null,
      "len_feat_sr": null
    },
    {
      "fold": 6,
      "instance_idx": 7,
      "prediction": 1,
      "len_binary_repr": 774,
      "len_theory": 549,
      "time_ext": 60.00149815692566,
      "status_ext": "Timeout",
      "len_raw_ext": null,
      "len_feat_ext": null,
      "time_cpi": 0.296305431984365,
      "status_cpi": "Success",
      "len_raw_cpi": 250,
      "len_feat_cpi": 91,
      "time_mcpi": 0.366017583059147,
      "status_mcpi": "Success",
      "len_raw_mcpi": 94,
      "len_feat_mcpi": 91,
      "time_sr": 1.4761928468942642e-05,
      "status_sr": "Error: ExplainerRF.sufficient_reason() got an unexpected keyword argument 'n'",
      "len_raw_sr": null,
      "len_feat_sr": null
    },
    {
      "fold": 6,
      "instance_idx": 8,
      "prediction": 1,
      "len_binary_repr": 774,
      "len_theory": 549,
      "time_ext": 60.00118483998813,
      "status_ext": "Timeout",
      "len_raw_ext": null,
      "len_feat_ext": null,
      "time_cpi": 0.4000071370974183,
      "status_cpi": "Success",
      "len_raw_cpi": 283,
      "len_feat_cpi": 102,
      "time_mcpi": 0.428414064925164,
      "status_mcpi": "Success",
      "len_raw_mcpi": 107,
      "len_feat_mcpi": 102,
      "time_sr": 1.5437835827469826e-05,
      "status_sr": "Error: ExplainerRF.sufficient_reason() got an unexpected keyword argument 'n'",
      "len_raw_sr": null,
      "len_feat_sr": null
    },
    {
      "fold": 6,
      "instance_idx": 9,
      "prediction": 0,
      "len_binary_repr": 774,
      "len_theory": 549,
      "time_ext": 60.001605378929526,
      "status_ext": "Timeout",
      "len_raw_ext": null,
      "len_feat_ext": null,
      "time_cpi": 0.33165460196323693,
      "status_cpi": "Success",
      "len_raw_cpi": 257,
      "len_feat_cpi": 87,
      "time_mcpi": 0.42845451598986983,
      "status_mcpi": "Success",
      "len_raw_mcpi": 94,
      "len_feat_mcpi": 87,
      "time_sr": 1.4468096196651459e-05,
      "status_sr": "Error: ExplainerRF.sufficient_reason() got an unexpected keyword argument 'n'",
      "len_raw_sr": null,
      "len_feat_sr": null
    },
    {
      "fold": 6,
      "instance_idx": 10,
      "prediction": 0,
      "len_binary_repr": 774,
      "len_theory": 549,
      "time_ext": 60.00138557283208,
      "status_ext": "Timeout",
      "len_raw_ext": null,
      "len_feat_ext": null,
      "time_cpi": 0.337092389119789,
      "status_cpi": "Success",
      "len_raw_cpi": 295,
      "len_feat_cpi": 97,
      "time_mcpi": 0.45033489307388663,
      "status_mcpi": "Success",
      "len_raw_mcpi": 109,
      "len_feat_mcpi": 97,
      "time_sr": 1.4744000509381294e-05,
      "status_sr": "Error: ExplainerRF.sufficient_reason() got an unexpected keyword argument 'n'",
      "len_raw_sr": null,
      "len_feat_sr": null
    },
    {
      "fold": 7,
      "instance_idx": 1,
      "prediction": 1,
      "len_binary_repr": 805,
      "len_theory": 575,
      "time_ext": 60.00290452782065,
      "status_ext": "Timeout",
      "len_raw_ext": null,
      "len_feat_ext": null,
      "time_cpi": 0.7836197479628026,
      "status_cpi": "Success",
      "len_raw_cpi": 304,
      "len_feat_cpi": 110,
      "time_mcpi": 1.3919305328745395,
      "status_mcpi": "Success",
      "len_raw_mcpi": 121,
      "len_feat_mcpi": 110,
      "time_sr": 1.606694422662258e-05,
      "status_sr": "Error: ExplainerRF.sufficient_reason() got an unexpected keyword argument 'n'",
      "len_raw_sr": null,
      "len_feat_sr": null
    },
    {
      "fold": 7,
      "instance_idx": 2,
      "prediction": 1,
      "len_binary_repr": 805,
      "len_theory": 575,
      "time_ext": 60.00181116187014,
      "status_ext": "Timeout",
      "len_raw_ext": null,
      "len_feat_ext": null,
      "time_cpi": 0.3388656391762197,
      "status_cpi": "Success",
      "len_raw_cpi": 254,
      "len_feat_cpi": 90,
      "time_mcpi": 0.42612972599454224,
      "status_mcpi": "Success",
      "len_raw_mcpi": 94,
      "len_feat_mcpi": 90,
      "time_sr": 1.275818794965744e-05,
      "status_sr": "Error: ExplainerRF.sufficient_reason() got an unexpected keyword argument 'n'",
      "len_raw_sr": null,
      "len_feat_sr": null
    },
    {
      "fold": 7,
      "instance_idx": 3,
      "prediction": 1,
      "len_binary_repr": 805,
      "len_theory": 575,
      "time_ext": 60.00177048705518,
      "status_ext": "Timeout",
      "len_raw_ext": null,
      "len_feat_ext": null,
      "time_cpi": 0.31964574893936515,
      "status_cpi": "Success",
      "len_raw_cpi": 291,
      "len_feat_cpi": 115,
      "time_mcpi": 0.40709460200741887,
      "status_mcpi": "Success",
      "len_raw_mcpi": 127,
      "len_feat_mcpi": 115,
      "time_sr": 1.2089032679796219e-05,
      "status_sr": "Error: ExplainerRF.sufficient_reason() got an unexpected keyword argument 'n'",
      "len_raw_sr": null,
      "len_feat_sr": null
    },
    {
      "fold": 7,
      "instance_idx": 4,
      "prediction": 1,
      "len_binary_repr": 805,
      "len_theory": 575,
      "time_ext": 60.0016486751847,
      "status_ext": "Timeout",
      "len_raw_ext": null,
      "len_feat_ext": null,
      "time_cpi": 0.4133007531054318,
      "status_cpi": "Success",
      "len_raw_cpi": 273,
      "len_feat_cpi": 104,
      "time_mcpi": 0.4168248809874058,
      "status_mcpi": "Success",
      "len_raw_mcpi": 108,
      "len_feat_mcpi": 104,
      "time_sr": 1.3978919014334679e-05,
      "status_sr": "Error: ExplainerRF.sufficient_reason() got an unexpected keyword argument 'n'",
      "len_raw_sr": null,
      "len_feat_sr": null
    },
    {
      "fold": 7,
      "instance_idx": 5,
      "prediction": 1,
      "len_binary_repr": 805,
      "len_theory": 575,
      "time_ext": 60.001592899207026,
      "status_ext": "Timeout",
      "len_raw_ext": null,
      "len_feat_ext": null,
      "time_cpi": 0.31205263803713024,
      "status_cpi": "Success",
      "len_raw_cpi": 260,
      "len_feat_cpi": 92,
      "time_mcpi": 0.3885393990203738,
      "status_mcpi": "Success",
      "len_raw_mcpi": 96,
      "len_feat_mcpi": 92,
      "time_sr": 1.32040586322546e-05,
      "status_sr": "Error: ExplainerRF.sufficient_reason() got an unexpected keyword argument 'n'",
      "len_raw_sr": null,
      "len_feat_sr": null
    },
    {
      "fold": 7,
      "instance_idx": 6,
      "prediction": 1,
      "len_binary_repr": 805,
      "len_theory": 575,
      "time_ext": 60.0018590639811,
      "status_ext": "Timeout",
      "len_raw_ext": null,
      "len_feat_ext": null,
      "time_cpi": 0.3432973891030997,
      "status_cpi": "Success",
      "len_raw_cpi": 266,
      "len_feat_cpi": 90,
      "time_mcpi": 0.4538876679725945,
      "status_mcpi": "Success",
      "len_raw_mcpi": 96,
      "len_feat_mcpi": 90,
      "time_sr": 1.2807082384824753e-05,
      "status_sr": "Error: ExplainerRF.sufficient_reason() got an unexpected keyword argument 'n'",
      "len_raw_sr": null,
      "len_feat_sr": null
    },
    {
      "fold": 7,
      "instance_idx": 7,
      "prediction": 0,
      "len_binary_repr": 805,
      "len_theory": 575,
      "time_ext": 60.00151396403089,
      "status_ext": "Timeout",
      "len_raw_ext": null,
      "len_feat_ext": null,
      "time_cpi": 0.3205202289391309,
      "status_cpi": "Success",
      "len_raw_cpi": 252,
      "len_feat_cpi": 80,
      "time_mcpi": 0.40342355193570256,
      "status_mcpi": "Success",
      "len_raw_mcpi": 87,
      "len_feat_mcpi": 80,
      "time_sr": 1.4337943866848946e-05,
      "status_sr": "Error: ExplainerRF.sufficient_reason() got an unexpected keyword argument 'n'",
      "len_raw_sr": null,
      "len_feat_sr": null
    },
    {
      "fold": 7,
      "instance_idx": 8,
      "prediction": 0,
      "len_binary_repr": 805,
      "len_theory": 575,
      "time_ext": 60.00145596801303,
      "status_ext": "Timeout",
      "len_raw_ext": null,
      "len_feat_ext": null,
      "time_cpi": 0.349198091076687,
      "status_cpi": "Success",
      "len_raw_cpi": 280,
      "len_feat_cpi": 92,
      "time_mcpi": 0.4548229039646685,
      "status_mcpi": "Success",
      "len_raw_mcpi": 101,
      "len_feat_mcpi": 92,
      "time_sr": 1.3316050171852112e-05,
      "status_sr": "Error: ExplainerRF.sufficient_reason() got an unexpected keyword argument 'n'",
      "len_raw_sr": null,
      "len_feat_sr": null
    },
    {
      "fold": 7,
      "instance_idx": 9,
      "prediction": 0,
      "len_binary_repr": 805,
      "len_theory": 575,
      "time_ext": 60.00179504510015,
      "status_ext": "Timeout",
      "len_raw_ext": null,
      "len_feat_ext": null,
      "time_cpi": 0.35214243503287435,
      "status_cpi": "Success",
      "len_raw_cpi": 248,
      "len_feat_cpi": 71,
      "time_mcpi": 0.4467259121593088,
      "status_mcpi": "Success",
      "len_raw_mcpi": 79,
      "len_feat_mcpi": 71,
      "time_sr": 1.2514181435108185e-05,
      "status_sr": "Error: ExplainerRF.sufficient_reason() got an unexpected keyword argument 'n'",
      "len_raw_sr": null,
      "len_feat_sr": null
    },
    {
      "fold": 7,
      "instance_idx": 10,
      "prediction": 0,
      "len_binary_repr": 805,
      "len_theory": 575,
      "time_ext": 60.00160228088498,
      "status_ext": "Timeout",
      "len_raw_ext": null,
      "len_feat_ext": null,
      "time_cpi": 0.3116457820869982,
      "status_cpi": "Success",
      "len_raw_cpi": 291,
      "len_feat_cpi": 99,
      "time_mcpi": 0.39992377907037735,
      "status_mcpi": "Success",
      "len_raw_mcpi": 106,
      "len_feat_mcpi": 99,
      "time_sr": 1.4493009075522423e-05,
      "status_sr": "Error: ExplainerRF.sufficient_reason() got an unexpected keyword argument 'n'",
      "len_raw_sr": null,
      "len_feat_sr": null
    },
    {
      "fold": 8,
      "instance_idx": 1,
      "prediction": 1,
      "len_binary_repr": 821,
      "len_theory": 585,
      "time_ext": 60.001457394100726,
      "status_ext": "Timeout",
      "len_raw_ext": null,
      "len_feat_ext": null,
      "time_cpi": 0.3624264649115503,
      "status_cpi": "Success",
      "len_raw_cpi": 291,
      "len_feat_cpi": 102,
      "time_mcpi": 0.47137731593102217,
      "status_mcpi": "Success",
      "len_raw_mcpi": 109,
      "len_feat_mcpi": 102,
      "time_sr": 1.292908564209938e-05,
      "status_sr": "Error: ExplainerRF.sufficient_reason() got an unexpected keyword argument 'n'",
      "len_raw_sr": null,
      "len_feat_sr": null
    },
    {
      "fold": 8,
      "instance_idx": 2,
      "prediction": 1,
      "len_binary_repr": 821,
      "len_theory": 585,
      "time_ext": 60.00116979307495,
      "status_ext": "Timeout",
      "len_raw_ext": null,
      "len_feat_ext": null,
      "time_cpi": 0.2223024230916053,
      "status_cpi": "Success",
      "len_raw_cpi": 275,
      "len_feat_cpi": 100,
      "time_mcpi": 0.27930985391139984,
      "status_mcpi": "Success",
      "len_raw_mcpi": 106,
      "len_feat_mcpi": 100,
      "time_sr": 9.248964488506317e-06,
      "status_sr": "Error: ExplainerRF.sufficient_reason() got an unexpected keyword argument 'n'",
      "len_raw_sr": null,
      "len_feat_sr": null
    },
    {
      "fold": 8,
      "instance_idx": 3,
      "prediction": 1,
      "len_binary_repr": 821,
      "len_theory": 585,
      "time_ext": 60.00156193296425,
      "status_ext": "Timeout",
      "len_raw_ext": null,
      "len_feat_ext": null,
      "time_cpi": 0.31956961704418063,
      "status_cpi": "Success",
      "len_raw_cpi": 270,
      "len_feat_cpi": 89,
      "time_mcpi": 0.3962477268651128,
      "status_mcpi": "Success",
      "len_raw_mcpi": 92,
      "len_feat_mcpi": 89,
      "time_sr": 1.2807082384824753e-05,
      "status_sr": "Error: ExplainerRF.sufficient_reason() got an unexpected keyword argument 'n'",
      "len_raw_sr": null,
      "len_feat_sr": null
    },
    {
      "fold": 8,
      "instance_idx": 4,
      "prediction": 0,
      "len_binary_repr": 821,
      "len_theory": 585,
      "time_ext": 60.00142919109203,
      "status_ext": "Timeout",
      "len_raw_ext": null,
      "len_feat_ext": null,
      "time_cpi": 0.3442990330513567,
      "status_cpi": "Success",
      "len_raw_cpi": 270,
      "len_feat_cpi": 99,
      "time_mcpi": 0.42815090413205326,
      "status_mcpi": "Success",
      "len_raw_mcpi": 109,
      "len_feat_mcpi": 99,
      "time_sr": 1.2343982234597206e-05,
      "status_sr": "Error: ExplainerRF.sufficient_reason() got an unexpected keyword argument 'n'",
      "len_raw_sr": null,
      "len_feat_sr": null
    },
    {
      "fold": 8,
      "instance_idx": 5,
      "prediction": 0,
      "len_binary_repr": 821,
      "len_theory": 585,
      "time_ext": 60.00134948012419,
      "status_ext": "Timeout",
      "len_raw_ext": null,
      "len_feat_ext": null,
      "time_cpi": 0.32998403697274625,
      "status_cpi": "Success",
      "len_raw_cpi": 274,
      "len_feat_cpi": 104,
      "time_mcpi": 0.4270197891164571,
      "status_mcpi": "Success",
      "len_raw_mcpi": 118,
      "len_feat_mcpi": 104,
      "time_sr": 1.1631986126303673e-05,
      "status_sr": "Error: ExplainerRF.sufficient_reason() got an unexpected keyword argument 'n'",
      "len_raw_sr": null,
      "len_feat_sr": null
    },
    {
      "fold": 8,
      "instance_idx": 6,
      "prediction": 0,
      "len_binary_repr": 821,
      "len_theory": 585,
      "time_ext": 60.001595091074705,
      "status_ext": "Timeout",
      "len_raw_ext": null,
      "len_feat_ext": null,
      "time_cpi": 0.34120488283224404,
      "status_cpi": "Success",
      "len_raw_cpi": 244,
      "len_feat_cpi": 76,
      "time_mcpi": 0.43356303102336824,
      "status_mcpi": "Success",
      "len_raw_mcpi": 81,
      "len_feat_mcpi": 76,
      "time_sr": 1.1055963113904e-05,
      "status_sr": "Error: ExplainerRF.sufficient_reason() got an unexpected keyword argument 'n'",
      "len_raw_sr": null,
      "len_feat_sr": null
    },
    {
      "fold": 8,
      "instance_idx": 7,
      "prediction": 0,
      "len_binary_repr": 821,
      "len_theory": 585,
      "time_ext": 60.001550272107124,
      "status_ext": "Timeout",
      "len_raw_ext": null,
      "len_feat_ext": null,
      "time_cpi": 0.33030456211417913,
      "status_cpi": "Success",
      "len_raw_cpi": 236,
      "len_feat_cpi": 84,
      "time_mcpi": 0.4042468380648643,
      "status_mcpi": "Success",
      "len_raw_mcpi": 92,
      "len_feat_mcpi": 84,
      "time_sr": 1.265713945031166e-05,
      "status_sr": "Error: ExplainerRF.sufficient_reason() got an unexpected keyword argument 'n'",
      "len_raw_sr": null,
      "len_feat_sr": null
    },
    {
      "fold": 8,
      "instance_idx": 8,
      "prediction": 0,
      "len_binary_repr": 821,
      "len_theory": 585,
      "time_ext": 60.001585345948115,
      "status_ext": "Timeout",
      "len_raw_ext": null,
      "len_feat_ext": null,
      "time_cpi": 0.3136055220384151,
      "status_cpi": "Success",
      "len_raw_cpi": 304,
      "len_feat_cpi": 101,
      "time_mcpi": 0.3961921399459243,
      "status_mcpi": "Success",
      "len_raw_mcpi": 106,
      "len_feat_mcpi": 101,
      "time_sr": 1.157587394118309e-05,
      "status_sr": "Error: ExplainerRF.sufficient_reason() got an unexpected keyword argument 'n'",
      "len_raw_sr": null,
      "len_feat_sr": null
    },
    {
      "fold": 8,
      "instance_idx": 9,
      "prediction": 0,
      "len_binary_repr": 821,
      "len_theory": 585,
      "time_ext": 60.00133295496926,
      "status_ext": "Timeout",
      "len_raw_ext": null,
      "len_feat_ext": null,
      "time_cpi": 0.33151440415531397,
      "status_cpi": "Success",
      "len_raw_cpi": 265,
      "len_feat_cpi": 91,
      "time_mcpi": 0.41757188783958554,
      "status_mcpi": "Success",
      "len_raw_mcpi": 101,
      "len_feat_mcpi": 91,
      "time_sr": 1.1485069990158081e-05,
      "status_sr": "Error: ExplainerRF.sufficient_reason() got an unexpected keyword argument 'n'",
      "len_raw_sr": null,
      "len_feat_sr": null
    },
    {
      "fold": 8,
      "instance_idx": 10,
      "prediction": 1,
      "len_binary_repr": 821,
      "len_theory": 585,
      "time_ext": 60.00124165718444,
      "status_ext": "Timeout",
      "len_raw_ext": null,
      "len_feat_ext": null,
      "time_cpi": 0.3147204820998013,
      "status_cpi": "Success",
      "len_raw_cpi": 266,
      "len_feat_cpi": 99,
      "time_mcpi": 0.39173167292028666,
      "status_mcpi": "Success",
      "len_raw_mcpi": 106,
      "len_feat_mcpi": 99,
      "time_sr": 1.2394972145557404e-05,
      "status_sr": "Error: ExplainerRF.sufficient_reason() got an unexpected keyword argument 'n'",
      "len_raw_sr": null,
      "len_feat_sr": null
    },
    {
      "fold": 9,
      "instance_idx": 1,
      "prediction": 1,
      "len_binary_repr": 769,
      "len_theory": 541,
      "time_ext": 60.001365965930745,
      "status_ext": "Timeout",
      "len_raw_ext": null,
      "len_feat_ext": null,
      "time_cpi": 0.3133216828573495,
      "status_cpi": "Success",
      "len_raw_cpi": 260,
      "len_feat_cpi": 92,
      "time_mcpi": 0.3995997828897089,
      "status_mcpi": "Success",
      "len_raw_mcpi": 98,
      "len_feat_mcpi": 92,
      "time_sr": 1.2094154953956604e-05,
      "status_sr": "Error: ExplainerRF.sufficient_reason() got an unexpected keyword argument 'n'",
      "len_raw_sr": null,
      "len_feat_sr": null
    },
    {
      "fold": 9,
      "instance_idx": 2,
      "prediction": 1,
      "len_binary_repr": 769,
      "len_theory": 541,
      "time_ext": 60.001368364086375,
      "status_ext": "Timeout",
      "len_raw_ext": null,
      "len_feat_ext": null,
      "time_cpi": 0.2937802979722619,
      "status_cpi": "Success",
      "len_raw_cpi": 249,
      "len_feat_cpi": 99,
      "time_mcpi": 0.36973852501250803,
      "status_mcpi": "Success",
      "len_raw_mcpi": 108,
      "len_feat_mcpi": 99,
      "time_sr": 1.2986129149794579e-05,
      "status_sr": "Error: ExplainerRF.sufficient_reason() got an unexpected keyword argument 'n'",
      "len_raw_sr": null,
      "len_feat_sr": null
    },
    {
      "fold": 9,
      "instance_idx": 3,
      "prediction": 1,
      "len_binary_repr": 769,
      "len_theory": 541,
      "time_ext": 60.00138309202157,
      "status_ext": "Timeout",
      "len_raw_ext": null,
      "len_feat_ext": null,
      "time_cpi": 0.31500541302375495,
      "status_cpi": "Success",
      "len_raw_cpi": 253,
      "len_feat_cpi": 94,
      "time_mcpi": 0.4043915050569922,
      "status_mcpi": "Success",
      "len_raw_mcpi": 103,
      "len_feat_mcpi": 94,
      "time_sr": 1.3659009709954262e-05,
      "status_sr": "Error: ExplainerRF.sufficient_reason() got an unexpected keyword argument 'n'",
      "len_raw_sr": null,
      "len_feat_sr": null
    },
    {
      "fold": 9,
      "instance_idx": 4,
      "prediction": 1,
      "len_binary_repr": 769,
      "len_theory": 541,
      "time_ext": 60.00125934602693,
      "status_ext": "Timeout",
      "len_raw_ext": null,
      "len_feat_ext": null,
      "time_cpi": 0.7284027410205454,
      "status_cpi": "Success",
      "len_raw_cpi": 262,
      "len_feat_cpi": 104,
      "time_mcpi": 1.0092120228800923,
      "status_mcpi": "Success",
      "len_raw_mcpi": 117,
      "len_feat_mcpi": 104,
      "time_sr": 1.3341894373297691e-05,
      "status_sr": "Error: ExplainerRF.sufficient_reason() got an unexpected keyword argument 'n'",
      "len_raw_sr": null,
      "len_feat_sr": null
    },
    {
      "fold": 9,
      "instance_idx": 5,
      "prediction": 0,
      "len_binary_repr": 769,
      "len_theory": 541,
      "time_ext": 60.00163533608429,
      "status_ext": "Timeout",
      "len_raw_ext": null,
      "len_feat_ext": null,
      "time_cpi": 0.29565915698185563,
      "status_cpi": "Success",
      "len_raw_cpi": 232,
      "len_feat_cpi": 86,
      "time_mcpi": 0.3612487749196589,
      "status_mcpi": "Success",
      "len_raw_mcpi": 94,
      "len_feat_mcpi": 86,
      "time_sr": 1.2763077393174171e-05,
      "status_sr": "Error: ExplainerRF.sufficient_reason() got an unexpected keyword argument 'n'",
      "len_raw_sr": null,
      "len_feat_sr": null
    },
    {
      "fold": 9,
      "instance_idx": 6,
      "prediction": 0,
      "len_binary_repr": 769,
      "len_theory": 541,
      "time_ext": 60.0013629978057,
      "status_ext": "Timeout",
      "len_raw_ext": null,
      "len_feat_ext": null,
      "time_cpi": 0.29537318111397326,
      "status_cpi": "Success",
      "len_raw_cpi": 286,
      "len_feat_cpi": 112,
      "time_mcpi": 0.37945200107060373,
      "status_mcpi": "Success",
      "len_raw_mcpi": 124,
      "len_feat_mcpi": 112,
      "time_sr": 1.2367963790893555e-05,
      "status_sr": "Error: ExplainerRF.sufficient_reason() got an unexpected keyword argument 'n'",
      "len_raw_sr": null,
      "len_feat_sr": null
    },
    {
      "fold": 9,
      "instance_idx": 7,
      "prediction": 0,
      "len_binary_repr": 769,
      "len_theory": 541,
      "time_ext": 60.00148124084808,
      "status_ext": "Timeout",
      "len_raw_ext": null,
      "len_feat_ext": null,
      "time_cpi": 0.3043763709720224,
      "status_cpi": "Success",
      "len_raw_cpi": 264,
      "len_feat_cpi": 100,
      "time_mcpi": 0.38747312501072884,
      "status_mcpi": "Success",
      "len_raw_mcpi": 114,
      "len_feat_mcpi": 100,
      "time_sr": 1.3022217899560928e-05,
      "status_sr": "Error: ExplainerRF.sufficient_reason() got an unexpected keyword argument 'n'",
      "len_raw_sr": null,
      "len_feat_sr": null
    },
    {
      "fold": 9,
      "instance_idx": 8,
      "prediction": 0,
      "len_binary_repr": 769,
      "len_theory": 541,
      "time_ext": 60.00096831098199,
      "status_ext": "Timeout",
      "len_raw_ext": null,
      "len_feat_ext": null,
      "time_cpi": 0.17141098901629448,
      "status_cpi": "Success",
      "len_raw_cpi": 232,
      "len_feat_cpi": 77,
      "time_mcpi": 0.21645159111358225,
      "status_mcpi": "Success",
      "len_raw_mcpi": 87,
      "len_feat_mcpi": 77,
      "time_sr": 9.494135156273842e-06,
      "status_sr": "Error: ExplainerRF.sufficient_reason() got an unexpected keyword argument 'n'",
      "len_raw_sr": null,
      "len_feat_sr": null
    },
    {
      "fold": 9,
      "instance_idx": 9,
      "prediction": 0,
      "len_binary_repr": 769,
      "len_theory": 541,
      "time_ext": 60.001475006807595,
      "status_ext": "Timeout",
      "len_raw_ext": null,
      "len_feat_ext": null,
      "time_cpi": 0.30249113496392965,
      "status_cpi": "Success",
      "len_raw_cpi": 267,
      "len_feat_cpi": 104,
      "time_mcpi": 0.3784009211231023,
      "status_mcpi": "Success",
      "len_raw_mcpi": 113,
      "len_feat_mcpi": 104,
      "time_sr": 1.1435011401772499e-05,
      "status_sr": "Error: ExplainerRF.sufficient_reason() got an unexpected keyword argument 'n'",
      "len_raw_sr": null,
      "len_feat_sr": null
    },
    {
      "fold": 9,
      "instance_idx": 10,
      "prediction": 0,
      "len_binary_repr": 769,
      "len_theory": 541,
      "time_ext": 60.00153995794244,
      "status_ext": "Timeout",
      "len_raw_ext": null,
      "len_feat_ext": null,
      "time_cpi": 0.28767748083919287,
      "status_cpi": "Success",
      "len_raw_cpi": 236,
      "len_feat_cpi": 74,
      "time_mcpi": 0.3596104048192501,
      "status_mcpi": "Success",
      "len_raw_mcpi": 77,
      "len_feat_mcpi": 74,
      "time_sr": 1.2126052752137184e-05,
      "status_sr": "Error: ExplainerRF.sufficient_reason() got an unexpected keyword argument 'n'",
      "len_raw_sr": null,
      "len_feat_sr": null
    },
    {
      "fold": 10,
      "instance_idx": 1,
      "prediction": 1,
      "len_binary_repr": 819,
      "len_theory": 588,
      "time_ext": 60.001124928938225,
      "status_ext": "Timeout",
      "len_raw_ext": null,
      "len_feat_ext": null,
      "time_cpi": 0.40323542011901736,
      "status_cpi": "Success",
      "len_raw_cpi": 271,
      "len_feat_cpi": 91,
      "time_mcpi": 0.3959398651495576,
      "status_mcpi": "Success",
      "len_raw_mcpi": 94,
      "len_feat_mcpi": 91,
      "time_sr": 1.1020107194781303e-05,
      "status_sr": "Error: ExplainerRF.sufficient_reason() got an unexpected keyword argument 'n'",
      "len_raw_sr": null,
      "len_feat_sr": null
    },
    {
      "fold": 10,
      "instance_idx": 2,
      "prediction": 1,
      "len_binary_repr": 819,
      "len_theory": 588,
      "time_ext": 60.0016520221252,
      "status_ext": "Timeout",
      "len_raw_ext": null,
      "len_feat_ext": null,
      "time_cpi": 0.31831859005615115,
      "status_cpi": "Success",
      "len_raw_cpi": 253,
      "len_feat_cpi": 93,
      "time_mcpi": 0.3951357929036021,
      "status_mcpi": "Success",
      "len_raw_mcpi": 102,
      "len_feat_mcpi": 93,
      "time_sr": 1.1598924174904823e-05,
      "status_sr": "Error: ExplainerRF.sufficient_reason() got an unexpected keyword argument 'n'",
      "len_raw_sr": null,
      "len_feat_sr": null
    },
    {
      "fold": 10,
      "instance_idx": 3,
      "prediction": 1,
      "len_binary_repr": 819,
      "len_theory": 588,
      "time_ext": 60.00181851303205,
      "status_ext": "Timeout",
      "len_raw_ext": null,
      "len_feat_ext": null,
      "time_cpi": 0.3175113380420953,
      "status_cpi": "Success",
      "len_raw_cpi": 282,
      "len_feat_cpi": 94,
      "time_mcpi": 0.4022380309179425,
      "status_mcpi": "Success",
      "len_raw_mcpi": 100,
      "len_feat_mcpi": 94,
      "time_sr": 1.2479955330491066e-05,
      "status_sr": "Error: ExplainerRF.sufficient_reason() got an unexpected keyword argument 'n'",
      "len_raw_sr": null,
      "len_feat_sr": null
    },
    {
      "fold": 10,
      "instance_idx": 4,
      "prediction": 1,
      "len_binary_repr": 819,
      "len_theory": 588,
      "time_ext": 60.001881869044155,
      "status_ext": "Timeout",
      "len_raw_ext": null,
      "len_feat_ext": null,
      "time_cpi": 0.3144576831255108,
      "status_cpi": "Success",
      "len_raw_cpi": 258,
      "len_feat_cpi": 89,
      "time_mcpi": 0.39051441103219986,
      "status_mcpi": "Success",
      "len_raw_mcpi": 95,
      "len_feat_mcpi": 89,
      "time_sr": 1.2591946870088577e-05,
      "status_sr": "Error: ExplainerRF.sufficient_reason() got an unexpected keyword argument 'n'",
      "len_raw_sr": null,
      "len_feat_sr": null
    },
    {
      "fold": 10,
      "instance_idx": 5,
      "prediction": 0,
      "len_binary_repr": 819,
      "len_theory": 588,
      "time_ext": 60.00187848811038,
      "status_ext": "Timeout",
      "len_raw_ext": null,
      "len_feat_ext": null,
      "time_cpi": 0.31409594882279634,
      "status_cpi": "Success",
      "len_raw_cpi": 321,
      "len_feat_cpi": 99,
      "time_mcpi": 0.40385446697473526,
      "status_mcpi": "Success",
      "len_raw_mcpi": 102,
      "len_feat_mcpi": 99,
      "time_sr": 1.1579133570194244e-05,
      "status_sr": "Error: ExplainerRF.sufficient_reason() got an unexpected keyword argument 'n'",
      "len_raw_sr": null,
      "len_feat_sr": null
    },
    {
      "fold": 10,
      "instance_idx": 6,
      "prediction": 0,
      "len_binary_repr": 819,
      "len_theory": 588,
      "time_ext": 60.001409450080246,
      "status_ext": "Timeout",
      "len_raw_ext": null,
      "len_feat_ext": null,
      "time_cpi": 0.49846560787409544,
      "status_cpi": "Success",
      "len_raw_cpi": 265,
      "len_feat_cpi": 84,
      "time_mcpi": 0.6345818480476737,
      "status_mcpi": "Success",
      "len_raw_mcpi": 90,
      "len_feat_mcpi": 84,
      "time_sr": 1.2869015336036682e-05,
      "status_sr": "Error: ExplainerRF.sufficient_reason() got an unexpected keyword argument 'n'",
      "len_raw_sr": null,
      "len_feat_sr": null
    },
    {
      "fold": 10,
      "instance_idx": 7,
      "prediction": 0,
      "len_binary_repr": 819,
      "len_theory": 588,
      "time_ext": 60.00163338100538,
      "status_ext": "Timeout",
      "len_raw_ext": null,
      "len_feat_ext": null,
      "time_cpi": 0.3493950061965734,
      "status_cpi": "Success",
      "len_raw_cpi": 255,
      "len_feat_cpi": 88,
      "time_mcpi": 0.4400255100335926,
      "status_mcpi": "Success",
      "len_raw_mcpi": 92,
      "len_feat_mcpi": 88,
      "time_sr": 1.8444843590259552e-05,
      "status_sr": "Error: ExplainerRF.sufficient_reason() got an unexpected keyword argument 'n'",
      "len_raw_sr": null,
      "len_feat_sr": null
    },
    {
      "fold": 10,
      "instance_idx": 8,
      "prediction": 0,
      "len_binary_repr": 819,
      "len_theory": 588,
      "time_ext": 60.001398036954924,
      "status_ext": "Timeout",
      "len_raw_ext": null,
      "len_feat_ext": null,
      "time_cpi": 0.3709802308585495,
      "status_cpi": "Success",
      "len_raw_cpi": 276,
      "len_feat_cpi": 100,
      "time_mcpi": 0.4756987621076405,
      "status_mcpi": "Success",
      "len_raw_mcpi": 108,
      "len_feat_mcpi": 100,
      "time_sr": 1.1109979823231697e-05,
      "status_sr": "Error: ExplainerRF.sufficient_reason() got an unexpected keyword argument 'n'",
      "len_raw_sr": null,
      "len_feat_sr": null
    },
    {
      "fold": 10,
      "instance_idx": 9,
      "prediction": 0,
      "len_binary_repr": 819,
      "len_theory": 588,
      "time_ext": 60.00136575009674,
      "status_ext": "Timeout",
      "len_raw_ext": null,
      "len_feat_ext": null,
      "time_cpi": 0.601572735933587,
      "status_cpi": "Success",
      "len_raw_cpi": 259,
      "len_feat_cpi": 80,
      "time_mcpi": 0.7553739119321108,
      "status_mcpi": "Success",
      "len_raw_mcpi": 88,
      "len_feat_mcpi": 80,
      "time_sr": 1.4613848179578781e-05,
      "status_sr": "Error: ExplainerRF.sufficient_reason() got an unexpected keyword argument 'n'",
      "len_raw_sr": null,
      "len_feat_sr": null
    },
    {
      "fold": 10,
      "instance_idx": 10,
      "prediction": 1,
      "len_binary_repr": 819,
      "len_theory": 588,
      "time_ext": 60.00104601192288,
      "status_ext": "Timeout",
      "len_raw_ext": null,
      "len_feat_ext": null,
      "time_cpi": 0.2480711319949478,
      "status_cpi": "Success",
      "len_raw_cpi": 284,
      "len_feat_cpi": 103,
      "time_mcpi": 0.24158145696856081,
      "status_mcpi": "Success",
      "len_raw_mcpi": 112,
      "len_feat_mcpi": 103,
      "time_sr": 8.811010047793388e-06,
      "status_sr": "Error: ExplainerRF.sufficient_reason() got an unexpected keyword argument 'n'",
      "len_raw_sr": null,
      "len_feat_sr": null
    }
  ]
}