{
  "dataset": "cnae_0",
  "dataset_metadata": {
    "n_instances": 1080,
    "n_features": 856,
    "avg_binary_features_size": 554.3,
    "avg_theory_clauses": 36.3
  },
  "model_performance": {
    "model_name": "RF",
    "accuracy_mean": 99.62962962962963,
    "accuracy_std": 0.7808092988070054,
    "parameters": {
      "max_depth": null,
      "random_state": 0
    }
  },
  "experiment_config": {
    "n_folds": 10,
    "total_instances": 100,
    "instances_per_fold": 10
  },
  "methods": {
    "external_cooper_amgoud": {
      "mean_time_s": 47.111178843965966,
      "std_time_s": 6.232670584284817,
      "timeout_count": 56,
      "timeout_percentage": 56.00000000000001,
      "mean_raw_size": 76.43181818181819,
      "mean_feature_size": 75.31818181818181,
      "std_feature_size": 12.358544219364484,
      "success_count": 44
    },
    "pyxai_cpi_xp": {
      "mean_time_s": 1.5532441941834987,
      "std_time_s": 1.7467429712490632,
      "timeout_count": 0,
      "timeout_percentage": 0.0,
      "mean_raw_size": 86.84,
      "mean_feature_size": 83.02,
      "std_feature_size": 11.230352090687454,
      "success_count": 100
    },
    "pyxai_m_cpi_xp": {
      "mean_time_s": 1.9222858095448465,
      "std_time_s": 1.867950271308842,
      "timeout_count": 0,
      "timeout_percentage": 0.0,
      "mean_raw_size": 83.13,
      "mean_feature_size": 83.02,
      "std_feature_size": 11.230352090687454,
      "success_count": 100
    },
    "pyxai_sufficient_reason": {
      "mean_time_s": 0.6953747782041318,
      "std_time_s": 0.28622465525745877,
      "timeout_count": 0,
      "timeout_percentage": 0.0,
      "mean_raw_size": 69.59,
      "mean_feature_size": 69.51,
      "std_feature_size": 13.031039091261288,
      "success_count": 100
    }
  },
  "detailed_results": [
    {
      "fold": 1,
      "instance_idx": 1,
      "prediction": 0,
      "len_binary_repr": 540,
      "len_theory": 30,
      "time_ext": 42.03252848586999,
      "status_ext": "Success",
      "len_raw_ext": 90,
      "len_feat_ext": 89,
      "time_cpi": 1.5303907168563455,
      "status_cpi": "Success",
      "len_raw_cpi": 89,
      "len_feat_cpi": 85,
      "time_mcpi": 2.120407667942345,
      "status_mcpi": "Success",
      "len_raw_mcpi": 86,
      "len_feat_mcpi": 85,
      "time_sr": 1.118007011944428,
      "status_sr": "Success",
      "len_raw_sr": 81,
      "len_feat_sr": 80
    },
    {
      "fold": 1,
      "instance_idx": 2,
      "prediction": 0,
      "len_binary_repr": 540,
      "len_theory": 30,
      "time_ext": 39.70611890708096,
      "status_ext": "Success",
      "len_raw_ext": 83,
      "len_feat_ext": 83,
      "time_cpi": 0.7493729158304632,
      "status_cpi": "Success",
      "len_raw_cpi": 79,
      "len_feat_cpi": 77,
      "time_mcpi": 1.0129433209076524,
      "status_mcpi": "Success",
      "len_raw_mcpi": 77,
      "len_feat_mcpi": 77,
      "time_sr": 0.49380267201922834,
      "status_sr": "Success",
      "len_raw_sr": 71,
      "len_feat_sr": 71
    },
    {
      "fold": 1,
      "instance_idx": 3,
      "prediction": 0,
      "len_binary_repr": 540,
      "len_theory": 30,
      "time_ext": 39.71459694788791,
      "status_ext": "Success",
      "len_raw_ext": 83,
      "len_feat_ext": 83,
      "time_cpi": 0.62620181706734,
      "status_cpi": "Success",
      "len_raw_cpi": 82,
      "len_feat_cpi": 79,
      "time_mcpi": 0.8801778259221464,
      "status_mcpi": "Success",
      "len_raw_mcpi": 80,
      "len_feat_mcpi": 79,
      "time_sr": 0.4511063448153436,
      "status_sr": "Success",
      "len_raw_sr": 64,
      "len_feat_sr": 64
    },
    {
      "fold": 1,
      "instance_idx": 4,
      "prediction": 1,
      "len_binary_repr": 540,
      "len_theory": 30,
      "time_ext": 30.519048815127462,
      "status_ext": "Success",
      "len_raw_ext": 56,
      "len_feat_ext": 56,
      "time_cpi": 0.526298605138436,
      "status_cpi": "Success",
      "len_raw_cpi": 70,
      "len_feat_cpi": 69,
      "time_mcpi": 0.6747912801802158,
      "status_mcpi": "Success",
      "len_raw_mcpi": 70,
      "len_feat_mcpi": 69,
      "time_sr": 0.1717380741611123,
      "status_sr": "Success",
      "len_raw_sr": 36,
      "len_feat_sr": 35
    },
    {
      "fold": 1,
      "instance_idx": 5,
      "prediction": 1,
      "len_binary_repr": 540,
      "len_theory": 30,
      "time_ext": 31.65613292204216,
      "status_ext": "Success",
      "len_raw_ext": 46,
      "len_feat_ext": 46,
      "time_cpi": 0.4768549050204456,
      "status_cpi": "Success",
      "len_raw_cpi": 49,
      "len_feat_cpi": 49,
      "time_mcpi": 0.5312546081840992,
      "status_mcpi": "Success",
      "len_raw_mcpi": 49,
      "len_feat_mcpi": 49,
      "time_sr": 0.15479119797237217,
      "status_sr": "Success",
      "len_raw_sr": 29,
      "len_feat_sr": 29
    },
    {
      "fold": 1,
      "instance_idx": 6,
      "prediction": 0,
      "len_binary_repr": 540,
      "len_theory": 30,
      "time_ext": 50.41146393097006,
      "status_ext": "Success",
      "len_raw_ext": 83,
      "len_feat_ext": 83,
      "time_cpi": 0.6674724039621651,
      "status_cpi": "Success",
      "len_raw_cpi": 78,
      "len_feat_cpi": 76,
      "time_mcpi": 0.9542393640149385,
      "status_mcpi": "Success",
      "len_raw_mcpi": 76,
      "len_feat_mcpi": 76,
      "time_sr": 0.5419146590866148,
      "status_sr": "Success",
      "len_raw_sr": 68,
      "len_feat_sr": 68
    },
    {
      "fold": 1,
      "instance_idx": 7,
      "prediction": 1,
      "len_binary_repr": 540,
      "len_theory": 30,
      "time_ext": 60.001535817980766,
      "status_ext": "Timeout",
      "len_raw_ext": null,
      "len_feat_ext": null,
      "time_cpi": 1.6914906359743327,
      "status_cpi": "Success",
      "len_raw_cpi": 125,
      "len_feat_cpi": 114,
      "time_mcpi": 2.1920486039016396,
      "status_mcpi": "Success",
      "len_raw_mcpi": 114,
      "len_feat_mcpi": 114,
      "time_sr": 0.30460511799901724,
      "status_sr": "Success",
      "len_raw_sr": 116,
      "len_feat_sr": 116
    },
    {
      "fold": 1,
      "instance_idx": 8,
      "prediction": 0,
      "len_binary_repr": 540,
      "len_theory": 30,
      "time_ext": 46.49927317397669,
      "status_ext": "Success",
      "len_raw_ext": 83,
      "len_feat_ext": 83,
      "time_cpi": 0.6832483138423413,
      "status_cpi": "Success",
      "len_raw_cpi": 82,
      "len_feat_cpi": 80,
      "time_mcpi": 0.949177284957841,
      "status_mcpi": "Success",
      "len_raw_mcpi": 80,
      "len_feat_mcpi": 80,
      "time_sr": 0.61256806505844,
      "status_sr": "Success",
      "len_raw_sr": 72,
      "len_feat_sr": 72
    },
    {
      "fold": 1,
      "instance_idx": 9,
      "prediction": 0,
      "len_binary_repr": 540,
      "len_theory": 30,
      "time_ext": 51.01059763785452,
      "status_ext": "Success",
      "len_raw_ext": 87,
      "len_feat_ext": 87,
      "time_cpi": 1.3298880811780691,
      "status_cpi": "Success",
      "len_raw_cpi": 87,
      "len_feat_cpi": 85,
      "time_mcpi": 1.75756999803707,
      "status_mcpi": "Success",
      "len_raw_mcpi": 85,
      "len_feat_mcpi": 85,
      "time_sr": 0.8349252128973603,
      "status_sr": "Success",
      "len_raw_sr": 76,
      "len_feat_sr": 76
    },
    {
      "fold": 1,
      "instance_idx": 10,
      "prediction": 0,
      "len_binary_repr": 540,
      "len_theory": 30,
      "time_ext": 45.97081303992309,
      "status_ext": "Success",
      "len_raw_ext": 84,
      "len_feat_ext": 84,
      "time_cpi": 0.8685991240199655,
      "status_cpi": "Success",
      "len_raw_cpi": 78,
      "len_feat_cpi": 76,
      "time_mcpi": 0.9791217148303986,
      "status_mcpi": "Success",
      "len_raw_mcpi": 76,
      "len_feat_mcpi": 76,
      "time_sr": 0.5026975709479302,
      "status_sr": "Success",
      "len_raw_sr": 62,
      "len_feat_sr": 62
    },
    {
      "fold": 2,
      "instance_idx": 1,
      "prediction": 0,
      "len_binary_repr": 534,
      "len_theory": 36,
      "time_ext": 60.01145413494669,
      "status_ext": "Timeout",
      "len_raw_ext": null,
      "len_feat_ext": null,
      "time_cpi": 4.323289718944579,
      "status_cpi": "Success",
      "len_raw_cpi": 97,
      "len_feat_cpi": 91,
      "time_mcpi": 4.802006579004228,
      "status_mcpi": "Success",
      "len_raw_mcpi": 91,
      "len_feat_mcpi": 91,
      "time_sr": 1.1371115769725293,
      "status_sr": "Success",
      "len_raw_sr": 82,
      "len_feat_sr": 82
    },
    {
      "fold": 2,
      "instance_idx": 2,
      "prediction": 0,
      "len_binary_repr": 534,
      "len_theory": 36,
      "time_ext": 60.001283696852624,
      "status_ext": "Timeout",
      "len_raw_ext": null,
      "len_feat_ext": null,
      "time_cpi": 3.0714704310521483,
      "status_cpi": "Success",
      "len_raw_cpi": 86,
      "len_feat_cpi": 83,
      "time_mcpi": 3.173248219070956,
      "status_mcpi": "Success",
      "len_raw_mcpi": 83,
      "len_feat_mcpi": 83,
      "time_sr": 0.7617779180873185,
      "status_sr": "Success",
      "len_raw_sr": 74,
      "len_feat_sr": 74
    },
    {
      "fold": 2,
      "instance_idx": 3,
      "prediction": 0,
      "len_binary_repr": 534,
      "len_theory": 36,
      "time_ext": 60.00139948888682,
      "status_ext": "Timeout",
      "len_raw_ext": null,
      "len_feat_ext": null,
      "time_cpi": 8.09865598520264,
      "status_cpi": "Success",
      "len_raw_cpi": 96,
      "len_feat_cpi": 89,
      "time_mcpi": 8.60008396487683,
      "status_mcpi": "Success",
      "len_raw_mcpi": 89,
      "len_feat_mcpi": 89,
      "time_sr": 1.4898278580512851,
      "status_sr": "Success",
      "len_raw_sr": 82,
      "len_feat_sr": 82
    },
    {
      "fold": 2,
      "instance_idx": 4,
      "prediction": 0,
      "len_binary_repr": 534,
      "len_theory": 36,
      "time_ext": 60.00121948705055,
      "status_ext": "Timeout",
      "len_raw_ext": null,
      "len_feat_ext": null,
      "time_cpi": 2.6208907710388303,
      "status_cpi": "Success",
      "len_raw_cpi": 96,
      "len_feat_cpi": 89,
      "time_mcpi": 3.1262371491175145,
      "status_mcpi": "Success",
      "len_raw_mcpi": 89,
      "len_feat_mcpi": 89,
      "time_sr": 1.0190786179155111,
      "status_sr": "Success",
      "len_raw_sr": 78,
      "len_feat_sr": 78
    },
    {
      "fold": 2,
      "instance_idx": 5,
      "prediction": 0,
      "len_binary_repr": 534,
      "len_theory": 36,
      "time_ext": 60.001083923038095,
      "status_ext": "Timeout",
      "len_raw_ext": null,
      "len_feat_ext": null,
      "time_cpi": 0.8263741740956903,
      "status_cpi": "Success",
      "len_raw_cpi": 93,
      "len_feat_cpi": 90,
      "time_mcpi": 1.1551096010953188,
      "status_mcpi": "Success",
      "len_raw_mcpi": 90,
      "len_feat_mcpi": 90,
      "time_sr": 0.5107046668417752,
      "status_sr": "Success",
      "len_raw_sr": 78,
      "len_feat_sr": 78
    },
    {
      "fold": 2,
      "instance_idx": 6,
      "prediction": 0,
      "len_binary_repr": 534,
      "len_theory": 36,
      "time_ext": 60.0009792658966,
      "status_ext": "Timeout",
      "len_raw_ext": null,
      "len_feat_ext": null,
      "time_cpi": 0.7369702199939638,
      "status_cpi": "Success",
      "len_raw_cpi": 90,
      "len_feat_cpi": 88,
      "time_mcpi": 1.0358373920898885,
      "status_mcpi": "Success",
      "len_raw_mcpi": 88,
      "len_feat_mcpi": 88,
      "time_sr": 0.5393163089174777,
      "status_sr": "Success",
      "len_raw_sr": 77,
      "len_feat_sr": 77
    },
    {
      "fold": 2,
      "instance_idx": 7,
      "prediction": 0,
      "len_binary_repr": 534,
      "len_theory": 36,
      "time_ext": 60.00145902018994,
      "status_ext": "Timeout",
      "len_raw_ext": null,
      "len_feat_ext": null,
      "time_cpi": 0.9768749561626464,
      "status_cpi": "Success",
      "len_raw_cpi": 85,
      "len_feat_cpi": 82,
      "time_mcpi": 1.462709761923179,
      "status_mcpi": "Success",
      "len_raw_mcpi": 82,
      "len_feat_mcpi": 82,
      "time_sr": 0.6049387590028346,
      "status_sr": "Success",
      "len_raw_sr": 66,
      "len_feat_sr": 66
    },
    {
      "fold": 2,
      "instance_idx": 8,
      "prediction": 0,
      "len_binary_repr": 534,
      "len_theory": 36,
      "time_ext": 60.00145207205787,
      "status_ext": "Timeout",
      "len_raw_ext": null,
      "len_feat_ext": null,
      "time_cpi": 6.000135332113132,
      "status_cpi": "Success",
      "len_raw_cpi": 88,
      "len_feat_cpi": 85,
      "time_mcpi": 6.891237412113696,
      "status_mcpi": "Success",
      "len_raw_mcpi": 85,
      "len_feat_mcpi": 85,
      "time_sr": 1.120065970113501,
      "status_sr": "Success",
      "len_raw_sr": 77,
      "len_feat_sr": 77
    },
    {
      "fold": 2,
      "instance_idx": 9,
      "prediction": 0,
      "len_binary_repr": 534,
      "len_theory": 36,
      "time_ext": 60.001167323905975,
      "status_ext": "Timeout",
      "len_raw_ext": null,
      "len_feat_ext": null,
      "time_cpi": 1.0918868607841432,
      "status_cpi": "Success",
      "len_raw_cpi": 90,
      "len_feat_cpi": 87,
      "time_mcpi": 1.4462905139662325,
      "status_mcpi": "Success",
      "len_raw_mcpi": 87,
      "len_feat_mcpi": 87,
      "time_sr": 0.8787957190070301,
      "status_sr": "Success",
      "len_raw_sr": 76,
      "len_feat_sr": 76
    },
    {
      "fold": 2,
      "instance_idx": 10,
      "prediction": 0,
      "len_binary_repr": 534,
      "len_theory": 36,
      "time_ext": 60.00149873900227,
      "status_ext": "Timeout",
      "len_raw_ext": null,
      "len_feat_ext": null,
      "time_cpi": 1.0537435000296682,
      "status_cpi": "Success",
      "len_raw_cpi": 87,
      "len_feat_cpi": 84,
      "time_mcpi": 1.388299309881404,
      "status_mcpi": "Success",
      "len_raw_mcpi": 84,
      "len_feat_mcpi": 84,
      "time_sr": 0.6931973770260811,
      "status_sr": "Success",
      "len_raw_sr": 76,
      "len_feat_sr": 76
    },
    {
      "fold": 3,
      "instance_idx": 1,
      "prediction": 0,
      "len_binary_repr": 550,
      "len_theory": 36,
      "time_ext": 60.00127981696278,
      "status_ext": "Timeout",
      "len_raw_ext": null,
      "len_feat_ext": null,
      "time_cpi": 0.7260721030179411,
      "status_cpi": "Success",
      "len_raw_cpi": 92,
      "len_feat_cpi": 83,
      "time_mcpi": 1.030451195081696,
      "status_mcpi": "Success",
      "len_raw_mcpi": 83,
      "len_feat_mcpi": 83,
      "time_sr": 0.6685514799319208,
      "status_sr": "Success",
      "len_raw_sr": 63,
      "len_feat_sr": 63
    },
    {
      "fold": 3,
      "instance_idx": 2,
      "prediction": 1,
      "len_binary_repr": 550,
      "len_theory": 36,
      "time_ext": 60.002077909884974,
      "status_ext": "Timeout",
      "len_raw_ext": null,
      "len_feat_ext": null,
      "time_cpi": 0.5339836711063981,
      "status_cpi": "Success",
      "len_raw_cpi": 78,
      "len_feat_cpi": 77,
      "time_mcpi": 0.6691187398973852,
      "status_mcpi": "Success",
      "len_raw_mcpi": 78,
      "len_feat_mcpi": 77,
      "time_sr": 0.48610895685851574,
      "status_sr": "Success",
      "len_raw_sr": 43,
      "len_feat_sr": 43
    },
    {
      "fold": 3,
      "instance_idx": 3,
      "prediction": 0,
      "len_binary_repr": 550,
      "len_theory": 36,
      "time_ext": 60.00169945182279,
      "status_ext": "Timeout",
      "len_raw_ext": null,
      "len_feat_ext": null,
      "time_cpi": 1.596824070904404,
      "status_cpi": "Success",
      "len_raw_cpi": 83,
      "len_feat_cpi": 78,
      "time_mcpi": 2.091300031170249,
      "status_mcpi": "Success",
      "len_raw_mcpi": 78,
      "len_feat_mcpi": 78,
      "time_sr": 1.140916576841846,
      "status_sr": "Success",
      "len_raw_sr": 64,
      "len_feat_sr": 64
    },
    {
      "fold": 3,
      "instance_idx": 4,
      "prediction": 0,
      "len_binary_repr": 550,
      "len_theory": 36,
      "time_ext": 60.00184867880307,
      "status_ext": "Timeout",
      "len_raw_ext": null,
      "len_feat_ext": null,
      "time_cpi": 0.8914858859498054,
      "status_cpi": "Success",
      "len_raw_cpi": 81,
      "len_feat_cpi": 76,
      "time_mcpi": 1.1838958461303264,
      "status_mcpi": "Success",
      "len_raw_mcpi": 76,
      "len_feat_mcpi": 76,
      "time_sr": 0.7093616048805416,
      "status_sr": "Success",
      "len_raw_sr": 61,
      "len_feat_sr": 61
    },
    {
      "fold": 3,
      "instance_idx": 5,
      "prediction": 0,
      "len_binary_repr": 550,
      "len_theory": 36,
      "time_ext": 60.00151067506522,
      "status_ext": "Timeout",
      "len_raw_ext": null,
      "len_feat_ext": null,
      "time_cpi": 1.207289048936218,
      "status_cpi": "Success",
      "len_raw_cpi": 81,
      "len_feat_cpi": 77,
      "time_mcpi": 1.6287862060125917,
      "status_mcpi": "Success",
      "len_raw_mcpi": 77,
      "len_feat_mcpi": 77,
      "time_sr": 0.8781481408514082,
      "status_sr": "Success",
      "len_raw_sr": 69,
      "len_feat_sr": 69
    },
    {
      "fold": 3,
      "instance_idx": 6,
      "prediction": 0,
      "len_binary_repr": 550,
      "len_theory": 36,
      "time_ext": 60.00189491407946,
      "status_ext": "Timeout",
      "len_raw_ext": null,
      "len_feat_ext": null,
      "time_cpi": 1.5945631149224937,
      "status_cpi": "Success",
      "len_raw_cpi": 92,
      "len_feat_cpi": 83,
      "time_mcpi": 2.002021389082074,
      "status_mcpi": "Success",
      "len_raw_mcpi": 84,
      "len_feat_mcpi": 83,
      "time_sr": 1.3418073910288513,
      "status_sr": "Success",
      "len_raw_sr": 66,
      "len_feat_sr": 65
    },
    {
      "fold": 3,
      "instance_idx": 7,
      "prediction": 0,
      "len_binary_repr": 550,
      "len_theory": 36,
      "time_ext": 60.001176497898996,
      "status_ext": "Timeout",
      "len_raw_ext": null,
      "len_feat_ext": null,
      "time_cpi": 0.6556035240646452,
      "status_cpi": "Success",
      "len_raw_cpi": 77,
      "len_feat_cpi": 74,
      "time_mcpi": 1.076280822046101,
      "status_mcpi": "Success",
      "len_raw_mcpi": 74,
      "len_feat_mcpi": 74,
      "time_sr": 0.6095236171968281,
      "status_sr": "Success",
      "len_raw_sr": 62,
      "len_feat_sr": 62
    },
    {
      "fold": 3,
      "instance_idx": 8,
      "prediction": 1,
      "len_binary_repr": 550,
      "len_theory": 36,
      "time_ext": 58.99462489411235,
      "status_ext": "Success",
      "len_raw_ext": 49,
      "len_feat_ext": 45,
      "time_cpi": 0.46551482495851815,
      "status_cpi": "Success",
      "len_raw_cpi": 44,
      "len_feat_cpi": 44,
      "time_mcpi": 0.5745620699599385,
      "status_mcpi": "Success",
      "len_raw_mcpi": 44,
      "len_feat_mcpi": 44,
      "time_sr": 0.15988458413630724,
      "status_sr": "Success",
      "len_raw_sr": 21,
      "len_feat_sr": 21
    },
    {
      "fold": 3,
      "instance_idx": 9,
      "prediction": 0,
      "len_binary_repr": 550,
      "len_theory": 36,
      "time_ext": 60.00119125517085,
      "status_ext": "Timeout",
      "len_raw_ext": null,
      "len_feat_ext": null,
      "time_cpi": 0.6734302670229226,
      "status_cpi": "Success",
      "len_raw_cpi": 82,
      "len_feat_cpi": 78,
      "time_mcpi": 0.936025463975966,
      "status_mcpi": "Success",
      "len_raw_mcpi": 78,
      "len_feat_mcpi": 78,
      "time_sr": 0.6886475598439574,
      "status_sr": "Success",
      "len_raw_sr": 64,
      "len_feat_sr": 64
    },
    {
      "fold": 3,
      "instance_idx": 10,
      "prediction": 0,
      "len_binary_repr": 550,
      "len_theory": 36,
      "time_ext": 60.00133787188679,
      "status_ext": "Timeout",
      "len_raw_ext": null,
      "len_feat_ext": null,
      "time_cpi": 0.9792319820262492,
      "status_cpi": "Success",
      "len_raw_cpi": 78,
      "len_feat_cpi": 72,
      "time_mcpi": 1.029871973907575,
      "status_mcpi": "Success",
      "len_raw_mcpi": 72,
      "len_feat_mcpi": 72,
      "time_sr": 0.7199321151711047,
      "status_sr": "Success",
      "len_raw_sr": 62,
      "len_feat_sr": 61
    },
    {
      "fold": 4,
      "instance_idx": 1,
      "prediction": 0,
      "len_binary_repr": 560,
      "len_theory": 39,
      "time_ext": 60.001067554811016,
      "status_ext": "Timeout",
      "len_raw_ext": null,
      "len_feat_ext": null,
      "time_cpi": 1.155144611140713,
      "status_cpi": "Success",
      "len_raw_cpi": 99,
      "len_feat_cpi": 92,
      "time_mcpi": 1.6335812599863857,
      "status_mcpi": "Success",
      "len_raw_mcpi": 92,
      "len_feat_mcpi": 92,
      "time_sr": 0.9969312660396099,
      "status_sr": "Success",
      "len_raw_sr": 81,
      "len_feat_sr": 81
    },
    {
      "fold": 4,
      "instance_idx": 2,
      "prediction": 0,
      "len_binary_repr": 560,
      "len_theory": 39,
      "time_ext": 60.001181839965284,
      "status_ext": "Timeout",
      "len_raw_ext": null,
      "len_feat_ext": null,
      "time_cpi": 1.0450849100016057,
      "status_cpi": "Success",
      "len_raw_cpi": 87,
      "len_feat_cpi": 84,
      "time_mcpi": 1.5323705519549549,
      "status_mcpi": "Success",
      "len_raw_mcpi": 84,
      "len_feat_mcpi": 84,
      "time_sr": 0.732784204185009,
      "status_sr": "Success",
      "len_raw_sr": 78,
      "len_feat_sr": 78
    },
    {
      "fold": 4,
      "instance_idx": 3,
      "prediction": 0,
      "len_binary_repr": 560,
      "len_theory": 39,
      "time_ext": 60.00129557913169,
      "status_ext": "Timeout",
      "len_raw_ext": null,
      "len_feat_ext": null,
      "time_cpi": 1.368304061004892,
      "status_cpi": "Success",
      "len_raw_cpi": 95,
      "len_feat_cpi": 93,
      "time_mcpi": 1.821039339993149,
      "status_mcpi": "Success",
      "len_raw_mcpi": 93,
      "len_feat_mcpi": 93,
      "time_sr": 1.042277456028387,
      "status_sr": "Success",
      "len_raw_sr": 78,
      "len_feat_sr": 78
    },
    {
      "fold": 4,
      "instance_idx": 4,
      "prediction": 0,
      "len_binary_repr": 560,
      "len_theory": 39,
      "time_ext": 60.001564502948895,
      "status_ext": "Timeout",
      "len_raw_ext": null,
      "len_feat_ext": null,
      "time_cpi": 1.3564836289733648,
      "status_cpi": "Success",
      "len_raw_cpi": 85,
      "len_feat_cpi": 83,
      "time_mcpi": 1.860278873005882,
      "status_mcpi": "Success",
      "len_raw_mcpi": 83,
      "len_feat_mcpi": 83,
      "time_sr": 0.7107175369746983,
      "status_sr": "Success",
      "len_raw_sr": 73,
      "len_feat_sr": 73
    },
    {
      "fold": 4,
      "instance_idx": 5,
      "prediction": 0,
      "len_binary_repr": 560,
      "len_theory": 39,
      "time_ext": 56.78847442497499,
      "status_ext": "Success",
      "len_raw_ext": 75,
      "len_feat_ext": 72,
      "time_cpi": 0.8989686120767146,
      "status_cpi": "Success",
      "len_raw_cpi": 83,
      "len_feat_cpi": 83,
      "time_mcpi": 1.0647964989766479,
      "status_mcpi": "Success",
      "len_raw_mcpi": 83,
      "len_feat_mcpi": 83,
      "time_sr": 0.5591944300103933,
      "status_sr": "Success",
      "len_raw_sr": 69,
      "len_feat_sr": 69
    },
    {
      "fold": 4,
      "instance_idx": 6,
      "prediction": 0,
      "len_binary_repr": 560,
      "len_theory": 39,
      "time_ext": 60.00130367092788,
      "status_ext": "Timeout",
      "len_raw_ext": null,
      "len_feat_ext": null,
      "time_cpi": 1.4109773179516196,
      "status_cpi": "Success",
      "len_raw_cpi": 99,
      "len_feat_cpi": 92,
      "time_mcpi": 1.7942730740178376,
      "status_mcpi": "Success",
      "len_raw_mcpi": 92,
      "len_feat_mcpi": 92,
      "time_sr": 1.316113332984969,
      "status_sr": "Success",
      "len_raw_sr": 81,
      "len_feat_sr": 81
    },
    {
      "fold": 4,
      "instance_idx": 7,
      "prediction": 0,
      "len_binary_repr": 560,
      "len_theory": 39,
      "time_ext": 60.00135307107121,
      "status_ext": "Timeout",
      "len_raw_ext": null,
      "len_feat_ext": null,
      "time_cpi": 0.7661758770700544,
      "status_cpi": "Success",
      "len_raw_cpi": 83,
      "len_feat_cpi": 81,
      "time_mcpi": 1.0731303070206195,
      "status_mcpi": "Success",
      "len_raw_mcpi": 81,
      "len_feat_mcpi": 81,
      "time_sr": 0.6506438530050218,
      "status_sr": "Success",
      "len_raw_sr": 67,
      "len_feat_sr": 67
    },
    {
      "fold": 4,
      "instance_idx": 8,
      "prediction": 0,
      "len_binary_repr": 560,
      "len_theory": 39,
      "time_ext": 60.0012875108514,
      "status_ext": "Timeout",
      "len_raw_ext": null,
      "len_feat_ext": null,
      "time_cpi": 0.760656394995749,
      "status_cpi": "Success",
      "len_raw_cpi": 91,
      "len_feat_cpi": 89,
      "time_mcpi": 1.0361933899112046,
      "status_mcpi": "Success",
      "len_raw_mcpi": 89,
      "len_feat_mcpi": 89,
      "time_sr": 0.5584976021200418,
      "status_sr": "Success",
      "len_raw_sr": 74,
      "len_feat_sr": 74
    },
    {
      "fold": 4,
      "instance_idx": 9,
      "prediction": 0,
      "len_binary_repr": 560,
      "len_theory": 39,
      "time_ext": 60.001285712001845,
      "status_ext": "Timeout",
      "len_raw_ext": null,
      "len_feat_ext": null,
      "time_cpi": 1.3118510849308223,
      "status_cpi": "Success",
      "len_raw_cpi": 94,
      "len_feat_cpi": 91,
      "time_mcpi": 1.7680158109869808,
      "status_mcpi": "Success",
      "len_raw_mcpi": 91,
      "len_feat_mcpi": 91,
      "time_sr": 0.7748717449139804,
      "status_sr": "Success",
      "len_raw_sr": 78,
      "len_feat_sr": 78
    },
    {
      "fold": 4,
      "instance_idx": 10,
      "prediction": 0,
      "len_binary_repr": 560,
      "len_theory": 39,
      "time_ext": 60.000984655926004,
      "status_ext": "Timeout",
      "len_raw_ext": null,
      "len_feat_ext": null,
      "time_cpi": 1.1948337138164788,
      "status_cpi": "Success",
      "len_raw_cpi": 90,
      "len_feat_cpi": 87,
      "time_mcpi": 1.5306204021908343,
      "status_mcpi": "Success",
      "len_raw_mcpi": 87,
      "len_feat_mcpi": 87,
      "time_sr": 0.6531639341264963,
      "status_sr": "Success",
      "len_raw_sr": 77,
      "len_feat_sr": 77
    },
    {
      "fold": 5,
      "instance_idx": 1,
      "prediction": 0,
      "len_binary_repr": 560,
      "len_theory": 41,
      "time_ext": 60.00144376303069,
      "status_ext": "Timeout",
      "len_raw_ext": null,
      "len_feat_ext": null,
      "time_cpi": 0.796487424056977,
      "status_cpi": "Success",
      "len_raw_cpi": 95,
      "len_feat_cpi": 89,
      "time_mcpi": 1.2211518920958042,
      "status_mcpi": "Success",
      "len_raw_mcpi": 89,
      "len_feat_mcpi": 89,
      "time_sr": 0.5679062909912318,
      "status_sr": "Success",
      "len_raw_sr": 67,
      "len_feat_sr": 67
    },
    {
      "fold": 5,
      "instance_idx": 2,
      "prediction": 0,
      "len_binary_repr": 560,
      "len_theory": 41,
      "time_ext": 60.00143779604696,
      "status_ext": "Timeout",
      "len_raw_ext": null,
      "len_feat_ext": null,
      "time_cpi": 0.6792613558936864,
      "status_cpi": "Success",
      "len_raw_cpi": 97,
      "len_feat_cpi": 89,
      "time_mcpi": 0.9514378888998181,
      "status_mcpi": "Success",
      "len_raw_mcpi": 89,
      "len_feat_mcpi": 89,
      "time_sr": 0.5422660131007433,
      "status_sr": "Success",
      "len_raw_sr": 73,
      "len_feat_sr": 73
    },
    {
      "fold": 5,
      "instance_idx": 3,
      "prediction": 0,
      "len_binary_repr": 560,
      "len_theory": 41,
      "time_ext": 60.00170324300416,
      "status_ext": "Timeout",
      "len_raw_ext": null,
      "len_feat_ext": null,
      "time_cpi": 2.6182855039369315,
      "status_cpi": "Success",
      "len_raw_cpi": 94,
      "len_feat_cpi": 88,
      "time_mcpi": 2.983222762821242,
      "status_mcpi": "Success",
      "len_raw_mcpi": 88,
      "len_feat_mcpi": 88,
      "time_sr": 0.7932634090539068,
      "status_sr": "Success",
      "len_raw_sr": 73,
      "len_feat_sr": 73
    },
    {
      "fold": 5,
      "instance_idx": 4,
      "prediction": 0,
      "len_binary_repr": 560,
      "len_theory": 41,
      "time_ext": 60.00097776390612,
      "status_ext": "Timeout",
      "len_raw_ext": null,
      "len_feat_ext": null,
      "time_cpi": 0.9265897141303867,
      "status_cpi": "Success",
      "len_raw_cpi": 90,
      "len_feat_cpi": 86,
      "time_mcpi": 1.2295391131192446,
      "status_mcpi": "Success",
      "len_raw_mcpi": 86,
      "len_feat_mcpi": 86,
      "time_sr": 0.5031469638925046,
      "status_sr": "Success",
      "len_raw_sr": 69,
      "len_feat_sr": 69
    },
    {
      "fold": 5,
      "instance_idx": 5,
      "prediction": 0,
      "len_binary_repr": 560,
      "len_theory": 41,
      "time_ext": 60.0015252828598,
      "status_ext": "Timeout",
      "len_raw_ext": null,
      "len_feat_ext": null,
      "time_cpi": 3.0339951280038804,
      "status_cpi": "Success",
      "len_raw_cpi": 98,
      "len_feat_cpi": 91,
      "time_mcpi": 3.5258143020328134,
      "status_mcpi": "Success",
      "len_raw_mcpi": 91,
      "len_feat_mcpi": 91,
      "time_sr": 0.8367060888558626,
      "status_sr": "Success",
      "len_raw_sr": 79,
      "len_feat_sr": 79
    },
    {
      "fold": 5,
      "instance_idx": 6,
      "prediction": 0,
      "len_binary_repr": 560,
      "len_theory": 41,
      "time_ext": 60.00123773701489,
      "status_ext": "Timeout",
      "len_raw_ext": null,
      "len_feat_ext": null,
      "time_cpi": 3.058145787101239,
      "status_cpi": "Success",
      "len_raw_cpi": 96,
      "len_feat_cpi": 89,
      "time_mcpi": 3.8345234969165176,
      "status_mcpi": "Success",
      "len_raw_mcpi": 89,
      "len_feat_mcpi": 89,
      "time_sr": 1.788122391095385,
      "status_sr": "Success",
      "len_raw_sr": 80,
      "len_feat_sr": 80
    },
    {
      "fold": 5,
      "instance_idx": 7,
      "prediction": 1,
      "len_binary_repr": 560,
      "len_theory": 41,
      "time_ext": 60.00149773992598,
      "status_ext": "Timeout",
      "len_raw_ext": null,
      "len_feat_ext": null,
      "time_cpi": 3.1060612199362367,
      "status_cpi": "Success",
      "len_raw_cpi": 113,
      "len_feat_cpi": 113,
      "time_mcpi": 3.7676624588202685,
      "status_mcpi": "Success",
      "len_raw_mcpi": 113,
      "len_feat_mcpi": 113,
      "time_sr": 0.4034839649684727,
      "status_sr": "Success",
      "len_raw_sr": 78,
      "len_feat_sr": 78
    },
    {
      "fold": 5,
      "instance_idx": 8,
      "prediction": 0,
      "len_binary_repr": 560,
      "len_theory": 41,
      "time_ext": 60.002003012923524,
      "status_ext": "Timeout",
      "len_raw_ext": null,
      "len_feat_ext": null,
      "time_cpi": 1.8279808030929416,
      "status_cpi": "Success",
      "len_raw_cpi": 105,
      "len_feat_cpi": 97,
      "time_mcpi": 2.266550486907363,
      "status_mcpi": "Success",
      "len_raw_mcpi": 98,
      "len_feat_mcpi": 97,
      "time_sr": 0.8571610311046243,
      "status_sr": "Success",
      "len_raw_sr": 83,
      "len_feat_sr": 82
    },
    {
      "fold": 5,
      "instance_idx": 9,
      "prediction": 0,
      "len_binary_repr": 560,
      "len_theory": 41,
      "time_ext": 60.00115320389159,
      "status_ext": "Timeout",
      "len_raw_ext": null,
      "len_feat_ext": null,
      "time_cpi": 2.6146024600602686,
      "status_cpi": "Success",
      "len_raw_cpi": 97,
      "len_feat_cpi": 91,
      "time_mcpi": 3.328344098990783,
      "status_mcpi": "Success",
      "len_raw_mcpi": 91,
      "len_feat_mcpi": 91,
      "time_sr": 0.8815469769760966,
      "status_sr": "Success",
      "len_raw_sr": 77,
      "len_feat_sr": 77
    },
    {
      "fold": 5,
      "instance_idx": 10,
      "prediction": 0,
      "len_binary_repr": 560,
      "len_theory": 41,
      "time_ext": 60.00137205305509,
      "status_ext": "Timeout",
      "len_raw_ext": null,
      "len_feat_ext": null,
      "time_cpi": 3.545699686044827,
      "status_cpi": "Success",
      "len_raw_cpi": 96,
      "len_feat_cpi": 89,
      "time_mcpi": 4.591991571011022,
      "status_mcpi": "Success",
      "len_raw_mcpi": 89,
      "len_feat_mcpi": 89,
      "time_sr": 1.056085324846208,
      "status_sr": "Success",
      "len_raw_sr": 80,
      "len_feat_sr": 80
    },
    {
      "fold": 6,
      "instance_idx": 1,
      "prediction": 1,
      "len_binary_repr": 554,
      "len_theory": 38,
      "time_ext": 60.00147578911856,
      "status_ext": "Timeout",
      "len_raw_ext": null,
      "len_feat_ext": null,
      "time_cpi": 2.754965036874637,
      "status_cpi": "Success",
      "len_raw_cpi": 140,
      "len_feat_cpi": 127,
      "time_mcpi": 3.7604072138201445,
      "status_mcpi": "Success",
      "len_raw_mcpi": 127,
      "len_feat_mcpi": 127,
      "time_sr": 0.3423763420432806,
      "status_sr": "Success",
      "len_raw_sr": 89,
      "len_feat_sr": 89
    },
    {
      "fold": 6,
      "instance_idx": 2,
      "prediction": 0,
      "len_binary_repr": 554,
      "len_theory": 38,
      "time_ext": 53.84331740997732,
      "status_ext": "Success",
      "len_raw_ext": 74,
      "len_feat_ext": 73,
      "time_cpi": 0.6632892431225628,
      "status_cpi": "Success",
      "len_raw_cpi": 84,
      "len_feat_cpi": 81,
      "time_mcpi": 1.0423500670585781,
      "status_mcpi": "Success",
      "len_raw_mcpi": 81,
      "len_feat_mcpi": 81,
      "time_sr": 0.4989464071113616,
      "status_sr": "Success",
      "len_raw_sr": 67,
      "len_feat_sr": 67
    },
    {
      "fold": 6,
      "instance_idx": 3,
      "prediction": 0,
      "len_binary_repr": 554,
      "len_theory": 38,
      "time_ext": 60.00243514101021,
      "status_ext": "Timeout",
      "len_raw_ext": null,
      "len_feat_ext": null,
      "time_cpi": 0.9842957751825452,
      "status_cpi": "Success",
      "len_raw_cpi": 86,
      "len_feat_cpi": 83,
      "time_mcpi": 1.2983986020553857,
      "status_mcpi": "Success",
      "len_raw_mcpi": 83,
      "len_feat_mcpi": 83,
      "time_sr": 0.804003241006285,
      "status_sr": "Success",
      "len_raw_sr": 72,
      "len_feat_sr": 72
    },
    {
      "fold": 6,
      "instance_idx": 4,
      "prediction": 0,
      "len_binary_repr": 554,
      "len_theory": 38,
      "time_ext": 53.446118977852166,
      "status_ext": "Success",
      "len_raw_ext": 85,
      "len_feat_ext": 82,
      "time_cpi": 0.6444406821392477,
      "status_cpi": "Success",
      "len_raw_cpi": 86,
      "len_feat_cpi": 83,
      "time_mcpi": 0.8952531199902296,
      "status_mcpi": "Success",
      "len_raw_mcpi": 83,
      "len_feat_mcpi": 83,
      "time_sr": 0.6311165241058916,
      "status_sr": "Success",
      "len_raw_sr": 68,
      "len_feat_sr": 68
    },
    {
      "fold": 6,
      "instance_idx": 5,
      "prediction": 0,
      "len_binary_repr": 554,
      "len_theory": 38,
      "time_ext": 54.571225226158276,
      "status_ext": "Success",
      "len_raw_ext": 85,
      "len_feat_ext": 84,
      "time_cpi": 0.7448786250315607,
      "status_cpi": "Success",
      "len_raw_cpi": 88,
      "len_feat_cpi": 86,
      "time_mcpi": 0.9768602680414915,
      "status_mcpi": "Success",
      "len_raw_mcpi": 86,
      "len_feat_mcpi": 86,
      "time_sr": 0.6691221459768713,
      "status_sr": "Success",
      "len_raw_sr": 67,
      "len_feat_sr": 67
    },
    {
      "fold": 6,
      "instance_idx": 6,
      "prediction": 0,
      "len_binary_repr": 554,
      "len_theory": 38,
      "time_ext": 58.471727007068694,
      "status_ext": "Success",
      "len_raw_ext": 76,
      "len_feat_ext": 74,
      "time_cpi": 0.8774449459742755,
      "status_cpi": "Success",
      "len_raw_cpi": 84,
      "len_feat_cpi": 83,
      "time_mcpi": 1.1831869061570615,
      "status_mcpi": "Success",
      "len_raw_mcpi": 83,
      "len_feat_mcpi": 83,
      "time_sr": 0.5503708419855684,
      "status_sr": "Success",
      "len_raw_sr": 69,
      "len_feat_sr": 69
    },
    {
      "fold": 6,
      "instance_idx": 7,
      "prediction": 1,
      "len_binary_repr": 554,
      "len_theory": 38,
      "time_ext": 60.00184764107689,
      "status_ext": "Timeout",
      "len_raw_ext": null,
      "len_feat_ext": null,
      "time_cpi": 1.0484359019901603,
      "status_cpi": "Success",
      "len_raw_cpi": 108,
      "len_feat_cpi": 104,
      "time_mcpi": 1.510627448093146,
      "status_mcpi": "Success",
      "len_raw_mcpi": 104,
      "len_feat_mcpi": 104,
      "time_sr": 0.39712724392302334,
      "status_sr": "Success",
      "len_raw_sr": 73,
      "len_feat_sr": 73
    },
    {
      "fold": 6,
      "instance_idx": 8,
      "prediction": 0,
      "len_binary_repr": 554,
      "len_theory": 38,
      "time_ext": 48.222696371842176,
      "status_ext": "Success",
      "len_raw_ext": 92,
      "len_feat_ext": 90,
      "time_cpi": 1.0837585481349379,
      "status_cpi": "Success",
      "len_raw_cpi": 86,
      "len_feat_cpi": 83,
      "time_mcpi": 1.2018767660483718,
      "status_mcpi": "Success",
      "len_raw_mcpi": 83,
      "len_feat_mcpi": 83,
      "time_sr": 0.6319343100767583,
      "status_sr": "Success",
      "len_raw_sr": 69,
      "len_feat_sr": 69
    },
    {
      "fold": 6,
      "instance_idx": 9,
      "prediction": 0,
      "len_binary_repr": 554,
      "len_theory": 38,
      "time_ext": 49.25818453799002,
      "status_ext": "Success",
      "len_raw_ext": 81,
      "len_feat_ext": 81,
      "time_cpi": 0.8653238851111382,
      "status_cpi": "Success",
      "len_raw_cpi": 81,
      "len_feat_cpi": 78,
      "time_mcpi": 1.1491599769797176,
      "status_mcpi": "Success",
      "len_raw_mcpi": 78,
      "len_feat_mcpi": 78,
      "time_sr": 0.5620126561261714,
      "status_sr": "Success",
      "len_raw_sr": 68,
      "len_feat_sr": 68
    },
    {
      "fold": 6,
      "instance_idx": 10,
      "prediction": 0,
      "len_binary_repr": 554,
      "len_theory": 38,
      "time_ext": 49.08147466694936,
      "status_ext": "Success",
      "len_raw_ext": 74,
      "len_feat_ext": 73,
      "time_cpi": 0.6357115781866014,
      "status_cpi": "Success",
      "len_raw_cpi": 85,
      "len_feat_cpi": 83,
      "time_mcpi": 1.01981184608303,
      "status_mcpi": "Success",
      "len_raw_mcpi": 83,
      "len_feat_mcpi": 83,
      "time_sr": 0.5794106482062489,
      "status_sr": "Success",
      "len_raw_sr": 66,
      "len_feat_sr": 66
    },
    {
      "fold": 7,
      "instance_idx": 1,
      "prediction": 0,
      "len_binary_repr": 570,
      "len_theory": 36,
      "time_ext": 45.90944055700675,
      "status_ext": "Success",
      "len_raw_ext": 74,
      "len_feat_ext": 74,
      "time_cpi": 0.7694754230324179,
      "status_cpi": "Success",
      "len_raw_cpi": 77,
      "len_feat_cpi": 75,
      "time_mcpi": 1.102647092193365,
      "status_mcpi": "Success",
      "len_raw_mcpi": 75,
      "len_feat_mcpi": 75,
      "time_sr": 0.6042216431815177,
      "status_sr": "Success",
      "len_raw_sr": 62,
      "len_feat_sr": 62
    },
    {
      "fold": 7,
      "instance_idx": 2,
      "prediction": 0,
      "len_binary_repr": 570,
      "len_theory": 36,
      "time_ext": 43.540649976115674,
      "status_ext": "Success",
      "len_raw_ext": 70,
      "len_feat_ext": 70,
      "time_cpi": 1.301252313889563,
      "status_cpi": "Success",
      "len_raw_cpi": 85,
      "len_feat_cpi": 80,
      "time_mcpi": 1.6384663321077824,
      "status_mcpi": "Success",
      "len_raw_mcpi": 80,
      "len_feat_mcpi": 80,
      "time_sr": 0.8147502271458507,
      "status_sr": "Success",
      "len_raw_sr": 61,
      "len_feat_sr": 61
    },
    {
      "fold": 7,
      "instance_idx": 3,
      "prediction": 0,
      "len_binary_repr": 570,
      "len_theory": 36,
      "time_ext": 48.78537840093486,
      "status_ext": "Success",
      "len_raw_ext": 81,
      "len_feat_ext": 81,
      "time_cpi": 7.92128059710376,
      "status_cpi": "Success",
      "len_raw_cpi": 82,
      "len_feat_cpi": 79,
      "time_mcpi": 8.306101538008079,
      "status_mcpi": "Success",
      "len_raw_mcpi": 79,
      "len_feat_mcpi": 79,
      "time_sr": 0.8297368639614433,
      "status_sr": "Success",
      "len_raw_sr": 68,
      "len_feat_sr": 68
    },
    {
      "fold": 7,
      "instance_idx": 4,
      "prediction": 0,
      "len_binary_repr": 570,
      "len_theory": 36,
      "time_ext": 43.37387921893969,
      "status_ext": "Success",
      "len_raw_ext": 75,
      "len_feat_ext": 75,
      "time_cpi": 1.2868446980137378,
      "status_cpi": "Success",
      "len_raw_cpi": 81,
      "len_feat_cpi": 76,
      "time_mcpi": 1.6473760670050979,
      "status_mcpi": "Success",
      "len_raw_mcpi": 76,
      "len_feat_mcpi": 76,
      "time_sr": 0.5133081830572337,
      "status_sr": "Success",
      "len_raw_sr": 59,
      "len_feat_sr": 59
    },
    {
      "fold": 7,
      "instance_idx": 5,
      "prediction": 0,
      "len_binary_repr": 570,
      "len_theory": 36,
      "time_ext": 53.7353087537922,
      "status_ext": "Success",
      "len_raw_ext": 76,
      "len_feat_ext": 76,
      "time_cpi": 4.0255364559125155,
      "status_cpi": "Success",
      "len_raw_cpi": 81,
      "len_feat_cpi": 78,
      "time_mcpi": 4.685418696841225,
      "status_mcpi": "Success",
      "len_raw_mcpi": 78,
      "len_feat_mcpi": 78,
      "time_sr": 1.0315746860578656,
      "status_sr": "Success",
      "len_raw_sr": 73,
      "len_feat_sr": 73
    },
    {
      "fold": 7,
      "instance_idx": 6,
      "prediction": 0,
      "len_binary_repr": 570,
      "len_theory": 36,
      "time_ext": 43.560008752858266,
      "status_ext": "Success",
      "len_raw_ext": 76,
      "len_feat_ext": 74,
      "time_cpi": 0.8018805210012943,
      "status_cpi": "Success",
      "len_raw_cpi": 71,
      "len_feat_cpi": 69,
      "time_mcpi": 1.0948260889854282,
      "status_mcpi": "Success",
      "len_raw_mcpi": 69,
      "len_feat_mcpi": 69,
      "time_sr": 0.6058594339992851,
      "status_sr": "Success",
      "len_raw_sr": 62,
      "len_feat_sr": 62
    },
    {
      "fold": 7,
      "instance_idx": 7,
      "prediction": 0,
      "len_binary_repr": 570,
      "len_theory": 36,
      "time_ext": 53.32771424110979,
      "status_ext": "Success",
      "len_raw_ext": 79,
      "len_feat_ext": 75,
      "time_cpi": 12.443783812923357,
      "status_cpi": "Success",
      "len_raw_cpi": 78,
      "len_feat_cpi": 75,
      "time_mcpi": 13.440425134031102,
      "status_mcpi": "Success",
      "len_raw_mcpi": 75,
      "len_feat_mcpi": 75,
      "time_sr": 0.8880563019774854,
      "status_sr": "Success",
      "len_raw_sr": 67,
      "len_feat_sr": 67
    },
    {
      "fold": 7,
      "instance_idx": 8,
      "prediction": 0,
      "len_binary_repr": 570,
      "len_theory": 36,
      "time_ext": 46.1017416799441,
      "status_ext": "Success",
      "len_raw_ext": 78,
      "len_feat_ext": 76,
      "time_cpi": 1.414726547896862,
      "status_cpi": "Success",
      "len_raw_cpi": 84,
      "len_feat_cpi": 79,
      "time_mcpi": 1.807262163842097,
      "status_mcpi": "Success",
      "len_raw_mcpi": 79,
      "len_feat_mcpi": 79,
      "time_sr": 0.9713908759877086,
      "status_sr": "Success",
      "len_raw_sr": 70,
      "len_feat_sr": 70
    },
    {
      "fold": 7,
      "instance_idx": 9,
      "prediction": 0,
      "len_binary_repr": 570,
      "len_theory": 36,
      "time_ext": 44.07036426104605,
      "status_ext": "Success",
      "len_raw_ext": 78,
      "len_feat_ext": 76,
      "time_cpi": 0.8568747479002923,
      "status_cpi": "Success",
      "len_raw_cpi": 68,
      "len_feat_cpi": 66,
      "time_mcpi": 1.3499314729124308,
      "status_mcpi": "Success",
      "len_raw_mcpi": 66,
      "len_feat_mcpi": 66,
      "time_sr": 0.6750376101117581,
      "status_sr": "Success",
      "len_raw_sr": 63,
      "len_feat_sr": 63
    },
    {
      "fold": 7,
      "instance_idx": 10,
      "prediction": 0,
      "len_binary_repr": 570,
      "len_theory": 36,
      "time_ext": 46.46631253394298,
      "status_ext": "Success",
      "len_raw_ext": 77,
      "len_feat_ext": 76,
      "time_cpi": 0.9863912588916719,
      "status_cpi": "Success",
      "len_raw_cpi": 87,
      "len_feat_cpi": 83,
      "time_mcpi": 1.3775176308117807,
      "status_mcpi": "Success",
      "len_raw_mcpi": 84,
      "len_feat_mcpi": 83,
      "time_sr": 0.7209710769820958,
      "status_sr": "Success",
      "len_raw_sr": 62,
      "len_feat_sr": 62
    },
    {
      "fold": 8,
      "instance_idx": 1,
      "prediction": 0,
      "len_binary_repr": 571,
      "len_theory": 44,
      "time_ext": 60.00110491993837,
      "status_ext": "Timeout",
      "len_raw_ext": null,
      "len_feat_ext": null,
      "time_cpi": 0.614468805026263,
      "status_cpi": "Success",
      "len_raw_cpi": 86,
      "len_feat_cpi": 83,
      "time_mcpi": 0.842694611987099,
      "status_mcpi": "Success",
      "len_raw_mcpi": 83,
      "len_feat_mcpi": 83,
      "time_sr": 0.6814669268205762,
      "status_sr": "Success",
      "len_raw_sr": 70,
      "len_feat_sr": 70
    },
    {
      "fold": 8,
      "instance_idx": 2,
      "prediction": 0,
      "len_binary_repr": 571,
      "len_theory": 44,
      "time_ext": 60.00255771889351,
      "status_ext": "Timeout",
      "len_raw_ext": null,
      "len_feat_ext": null,
      "time_cpi": 1.1333994648884982,
      "status_cpi": "Success",
      "len_raw_cpi": 98,
      "len_feat_cpi": 88,
      "time_mcpi": 1.5092264669947326,
      "status_mcpi": "Success",
      "len_raw_mcpi": 89,
      "len_feat_mcpi": 88,
      "time_sr": 0.8941886841785163,
      "status_sr": "Success",
      "len_raw_sr": 75,
      "len_feat_sr": 75
    },
    {
      "fold": 8,
      "instance_idx": 3,
      "prediction": 0,
      "len_binary_repr": 571,
      "len_theory": 44,
      "time_ext": 60.001264987979084,
      "status_ext": "Timeout",
      "len_raw_ext": null,
      "len_feat_ext": null,
      "time_cpi": 1.1447073000017554,
      "status_cpi": "Success",
      "len_raw_cpi": 88,
      "len_feat_cpi": 84,
      "time_mcpi": 1.49569571018219,
      "status_mcpi": "Success",
      "len_raw_mcpi": 84,
      "len_feat_mcpi": 84,
      "time_sr": 0.7737134830094874,
      "status_sr": "Success",
      "len_raw_sr": 73,
      "len_feat_sr": 73
    },
    {
      "fold": 8,
      "instance_idx": 4,
      "prediction": 0,
      "len_binary_repr": 571,
      "len_theory": 44,
      "time_ext": 60.00106535782106,
      "status_ext": "Timeout",
      "len_raw_ext": null,
      "len_feat_ext": null,
      "time_cpi": 0.8008239830378443,
      "status_cpi": "Success",
      "len_raw_cpi": 93,
      "len_feat_cpi": 84,
      "time_mcpi": 0.9191781978588551,
      "status_mcpi": "Success",
      "len_raw_mcpi": 85,
      "len_feat_mcpi": 84,
      "time_sr": 0.6060199129860848,
      "status_sr": "Success",
      "len_raw_sr": 73,
      "len_feat_sr": 72
    },
    {
      "fold": 8,
      "instance_idx": 5,
      "prediction": 0,
      "len_binary_repr": 571,
      "len_theory": 44,
      "time_ext": 60.0011272970587,
      "status_ext": "Timeout",
      "len_raw_ext": null,
      "len_feat_ext": null,
      "time_cpi": 0.6921677310019732,
      "status_cpi": "Success",
      "len_raw_cpi": 89,
      "len_feat_cpi": 83,
      "time_mcpi": 0.977890603011474,
      "status_mcpi": "Success",
      "len_raw_mcpi": 84,
      "len_feat_mcpi": 83,
      "time_sr": 0.6070086539257318,
      "status_sr": "Success",
      "len_raw_sr": 71,
      "len_feat_sr": 71
    },
    {
      "fold": 8,
      "instance_idx": 6,
      "prediction": 0,
      "len_binary_repr": 571,
      "len_theory": 44,
      "time_ext": 60.00137257599272,
      "status_ext": "Timeout",
      "len_raw_ext": null,
      "len_feat_ext": null,
      "time_cpi": 0.8093750211410224,
      "status_cpi": "Success",
      "len_raw_cpi": 86,
      "len_feat_cpi": 82,
      "time_mcpi": 1.3256197748705745,
      "status_mcpi": "Success",
      "len_raw_mcpi": 82,
      "len_feat_mcpi": 82,
      "time_sr": 0.8233322170563042,
      "status_sr": "Success",
      "len_raw_sr": 72,
      "len_feat_sr": 72
    },
    {
      "fold": 8,
      "instance_idx": 7,
      "prediction": 0,
      "len_binary_repr": 571,
      "len_theory": 44,
      "time_ext": 60.00112985796295,
      "status_ext": "Timeout",
      "len_raw_ext": null,
      "len_feat_ext": null,
      "time_cpi": 0.5947220160160214,
      "status_cpi": "Success",
      "len_raw_cpi": 88,
      "len_feat_cpi": 82,
      "time_mcpi": 0.8351600868627429,
      "status_mcpi": "Success",
      "len_raw_mcpi": 82,
      "len_feat_mcpi": 82,
      "time_sr": 0.5271175031084567,
      "status_sr": "Success",
      "len_raw_sr": 66,
      "len_feat_sr": 66
    },
    {
      "fold": 8,
      "instance_idx": 8,
      "prediction": 0,
      "len_binary_repr": 571,
      "len_theory": 44,
      "time_ext": 60.001258020987734,
      "status_ext": "Timeout",
      "len_raw_ext": null,
      "len_feat_ext": null,
      "time_cpi": 3.026721335016191,
      "status_cpi": "Success",
      "len_raw_cpi": 100,
      "len_feat_cpi": 92,
      "time_mcpi": 3.6606189250014722,
      "status_mcpi": "Success",
      "len_raw_mcpi": 92,
      "len_feat_mcpi": 92,
      "time_sr": 1.1397084060590714,
      "status_sr": "Success",
      "len_raw_sr": 84,
      "len_feat_sr": 83
    },
    {
      "fold": 8,
      "instance_idx": 9,
      "prediction": 0,
      "len_binary_repr": 571,
      "len_theory": 44,
      "time_ext": 60.00136767420918,
      "status_ext": "Timeout",
      "len_raw_ext": null,
      "len_feat_ext": null,
      "time_cpi": 1.1831204688642174,
      "status_cpi": "Success",
      "len_raw_cpi": 91,
      "len_feat_cpi": 87,
      "time_mcpi": 1.4532507359981537,
      "status_mcpi": "Success",
      "len_raw_mcpi": 87,
      "len_feat_mcpi": 87,
      "time_sr": 0.8012419999577105,
      "status_sr": "Success",
      "len_raw_sr": 76,
      "len_feat_sr": 76
    },
    {
      "fold": 8,
      "instance_idx": 10,
      "prediction": 0,
      "len_binary_repr": 571,
      "len_theory": 44,
      "time_ext": 60.00079755904153,
      "status_ext": "Timeout",
      "len_raw_ext": null,
      "len_feat_ext": null,
      "time_cpi": 0.6139010319020599,
      "status_cpi": "Success",
      "len_raw_cpi": 85,
      "len_feat_cpi": 82,
      "time_mcpi": 0.8873949581757188,
      "status_mcpi": "Success",
      "len_raw_mcpi": 82,
      "len_feat_mcpi": 82,
      "time_sr": 0.4064449390862137,
      "status_sr": "Success",
      "len_raw_sr": 71,
      "len_feat_sr": 70
    },
    {
      "fold": 9,
      "instance_idx": 1,
      "prediction": 0,
      "len_binary_repr": 547,
      "len_theory": 34,
      "time_ext": 46.422190675046295,
      "status_ext": "Success",
      "len_raw_ext": 87,
      "len_feat_ext": 85,
      "time_cpi": 1.012131470022723,
      "status_cpi": "Success",
      "len_raw_cpi": 92,
      "len_feat_cpi": 90,
      "time_mcpi": 1.5177689068950713,
      "status_mcpi": "Success",
      "len_raw_mcpi": 90,
      "len_feat_mcpi": 90,
      "time_sr": 0.6708978931419551,
      "status_sr": "Success",
      "len_raw_sr": 72,
      "len_feat_sr": 72
    },
    {
      "fold": 9,
      "instance_idx": 2,
      "prediction": 0,
      "len_binary_repr": 547,
      "len_theory": 34,
      "time_ext": 44.66431218595244,
      "status_ext": "Success",
      "len_raw_ext": 84,
      "len_feat_ext": 82,
      "time_cpi": 3.6448825418483466,
      "status_cpi": "Success",
      "len_raw_cpi": 92,
      "len_feat_cpi": 88,
      "time_mcpi": 4.030232855118811,
      "status_mcpi": "Success",
      "len_raw_mcpi": 89,
      "len_feat_mcpi": 88,
      "time_sr": 0.8623921959660947,
      "status_sr": "Success",
      "len_raw_sr": 70,
      "len_feat_sr": 70
    },
    {
      "fold": 9,
      "instance_idx": 3,
      "prediction": 0,
      "len_binary_repr": 547,
      "len_theory": 34,
      "time_ext": 52.81075125397183,
      "status_ext": "Success",
      "len_raw_ext": 80,
      "len_feat_ext": 80,
      "time_cpi": 1.456903467187658,
      "status_cpi": "Success",
      "len_raw_cpi": 88,
      "len_feat_cpi": 86,
      "time_mcpi": 1.8826087941415608,
      "status_mcpi": "Success",
      "len_raw_mcpi": 86,
      "len_feat_mcpi": 86,
      "time_sr": 1.2524911230430007,
      "status_sr": "Success",
      "len_raw_sr": 71,
      "len_feat_sr": 71
    },
    {
      "fold": 9,
      "instance_idx": 4,
      "prediction": 0,
      "len_binary_repr": 547,
      "len_theory": 34,
      "time_ext": 41.355072379112244,
      "status_ext": "Success",
      "len_raw_ext": 84,
      "len_feat_ext": 84,
      "time_cpi": 0.6178120081312954,
      "status_cpi": "Success",
      "len_raw_cpi": 76,
      "len_feat_cpi": 74,
      "time_mcpi": 0.8670679009519517,
      "status_mcpi": "Success",
      "len_raw_mcpi": 74,
      "len_feat_mcpi": 74,
      "time_sr": 0.5078748459927738,
      "status_sr": "Success",
      "len_raw_sr": 58,
      "len_feat_sr": 58
    },
    {
      "fold": 9,
      "instance_idx": 5,
      "prediction": 0,
      "len_binary_repr": 547,
      "len_theory": 34,
      "time_ext": 40.15846615983173,
      "status_ext": "Success",
      "len_raw_ext": 77,
      "len_feat_ext": 77,
      "time_cpi": 0.839777949033305,
      "status_cpi": "Success",
      "len_raw_cpi": 79,
      "len_feat_cpi": 77,
      "time_mcpi": 1.070525489980355,
      "status_mcpi": "Success",
      "len_raw_mcpi": 77,
      "len_feat_mcpi": 77,
      "time_sr": 0.5027336310595274,
      "status_sr": "Success",
      "len_raw_sr": 61,
      "len_feat_sr": 61
    },
    {
      "fold": 9,
      "instance_idx": 6,
      "prediction": 1,
      "len_binary_repr": 547,
      "len_theory": 34,
      "time_ext": 60.00118413986638,
      "status_ext": "Timeout",
      "len_raw_ext": null,
      "len_feat_ext": null,
      "time_cpi": 1.3623843821696937,
      "status_cpi": "Success",
      "len_raw_cpi": 95,
      "len_feat_cpi": 93,
      "time_mcpi": 1.7332758831325918,
      "status_mcpi": "Success",
      "len_raw_mcpi": 93,
      "len_feat_mcpi": 93,
      "time_sr": 0.3390514780767262,
      "status_sr": "Success",
      "len_raw_sr": 72,
      "len_feat_sr": 72
    },
    {
      "fold": 9,
      "instance_idx": 7,
      "prediction": 0,
      "len_binary_repr": 547,
      "len_theory": 34,
      "time_ext": 43.45268401084468,
      "status_ext": "Success",
      "len_raw_ext": 82,
      "len_feat_ext": 81,
      "time_cpi": 0.5932697241660208,
      "status_cpi": "Success",
      "len_raw_cpi": 74,
      "len_feat_cpi": 72,
      "time_mcpi": 0.8348796078935266,
      "status_mcpi": "Success",
      "len_raw_mcpi": 72,
      "len_feat_mcpi": 72,
      "time_sr": 0.6415853120852262,
      "status_sr": "Success",
      "len_raw_sr": 62,
      "len_feat_sr": 62
    },
    {
      "fold": 9,
      "instance_idx": 8,
      "prediction": 0,
      "len_binary_repr": 547,
      "len_theory": 34,
      "time_ext": 47.168197934981436,
      "status_ext": "Success",
      "len_raw_ext": 82,
      "len_feat_ext": 81,
      "time_cpi": 2.7835271661169827,
      "status_cpi": "Success",
      "len_raw_cpi": 93,
      "len_feat_cpi": 90,
      "time_mcpi": 3.148696003947407,
      "status_mcpi": "Success",
      "len_raw_mcpi": 90,
      "len_feat_mcpi": 90,
      "time_sr": 0.976624172879383,
      "status_sr": "Success",
      "len_raw_sr": 69,
      "len_feat_sr": 69
    },
    {
      "fold": 9,
      "instance_idx": 9,
      "prediction": 0,
      "len_binary_repr": 547,
      "len_theory": 34,
      "time_ext": 38.333038365934044,
      "status_ext": "Success",
      "len_raw_ext": 79,
      "len_feat_ext": 78,
      "time_cpi": 0.6892290159594268,
      "status_cpi": "Success",
      "len_raw_cpi": 87,
      "len_feat_cpi": 85,
      "time_mcpi": 0.76640868303366,
      "status_mcpi": "Success",
      "len_raw_mcpi": 85,
      "len_feat_mcpi": 85,
      "time_sr": 0.4437870569527149,
      "status_sr": "Success",
      "len_raw_sr": 60,
      "len_feat_sr": 60
    },
    {
      "fold": 9,
      "instance_idx": 10,
      "prediction": 0,
      "len_binary_repr": 547,
      "len_theory": 34,
      "time_ext": 60.00101123820059,
      "status_ext": "Timeout",
      "len_raw_ext": null,
      "len_feat_ext": null,
      "time_cpi": 0.6422176579944789,
      "status_cpi": "Success",
      "len_raw_cpi": 73,
      "len_feat_cpi": 71,
      "time_mcpi": 0.8808298469521105,
      "status_mcpi": "Success",
      "len_raw_mcpi": 71,
      "len_feat_mcpi": 71,
      "time_sr": 0.42521297303028405,
      "status_sr": "Success",
      "len_raw_sr": 60,
      "len_feat_sr": 60
    },
    {
      "fold": 10,
      "instance_idx": 1,
      "prediction": 0,
      "len_binary_repr": 557,
      "len_theory": 29,
      "time_ext": 60.00155037594959,
      "status_ext": "Timeout",
      "len_raw_ext": null,
      "len_feat_ext": null,
      "time_cpi": 1.0812306799925864,
      "status_cpi": "Success",
      "len_raw_cpi": 115,
      "len_feat_cpi": 108,
      "time_mcpi": 1.3402794911526144,
      "status_mcpi": "Success",
      "len_raw_mcpi": 108,
      "len_feat_mcpi": 108,
      "time_sr": 0.39895547390915453,
      "status_sr": "Success",
      "len_raw_sr": 98,
      "len_feat_sr": 98
    },
    {
      "fold": 10,
      "instance_idx": 2,
      "prediction": 0,
      "len_binary_repr": 557,
      "len_theory": 29,
      "time_ext": 57.21278601209633,
      "status_ext": "Success",
      "len_raw_ext": 84,
      "len_feat_ext": 83,
      "time_cpi": 0.9680007700808346,
      "status_cpi": "Success",
      "len_raw_cpi": 84,
      "len_feat_cpi": 81,
      "time_mcpi": 1.4835225830320269,
      "status_mcpi": "Success",
      "len_raw_mcpi": 81,
      "len_feat_mcpi": 81,
      "time_sr": 0.6899036541581154,
      "status_sr": "Success",
      "len_raw_sr": 72,
      "len_feat_sr": 72
    },
    {
      "fold": 10,
      "instance_idx": 3,
      "prediction": 0,
      "len_binary_repr": 557,
      "len_theory": 29,
      "time_ext": 48.156743637053296,
      "status_ext": "Success",
      "len_raw_ext": 83,
      "len_feat_ext": 78,
      "time_cpi": 0.698158600134775,
      "status_cpi": "Success",
      "len_raw_cpi": 83,
      "len_feat_cpi": 80,
      "time_mcpi": 0.9915664650034159,
      "status_mcpi": "Success",
      "len_raw_mcpi": 80,
      "len_feat_mcpi": 80,
      "time_sr": 0.509726817952469,
      "status_sr": "Success",
      "len_raw_sr": 68,
      "len_feat_sr": 68
    },
    {
      "fold": 10,
      "instance_idx": 4,
      "prediction": 1,
      "len_binary_repr": 557,
      "len_theory": 29,
      "time_ext": 44.32622825214639,
      "status_ext": "Success",
      "len_raw_ext": 22,
      "len_feat_ext": 22,
      "time_cpi": 0.4201619268860668,
      "status_cpi": "Success",
      "len_raw_cpi": 48,
      "len_feat_cpi": 48,
      "time_mcpi": 0.5157838880550116,
      "status_mcpi": "Success",
      "len_raw_mcpi": 48,
      "len_feat_mcpi": 48,
      "time_sr": 0.13453380204737186,
      "status_sr": "Success",
      "len_raw_sr": 21,
      "len_feat_sr": 21
    },
    {
      "fold": 10,
      "instance_idx": 5,
      "prediction": 0,
      "len_binary_repr": 557,
      "len_theory": 29,
      "time_ext": 45.6076859110035,
      "status_ext": "Success",
      "len_raw_ext": 75,
      "len_feat_ext": 72,
      "time_cpi": 0.771914100041613,
      "status_cpi": "Success",
      "len_raw_cpi": 71,
      "len_feat_cpi": 69,
      "time_mcpi": 0.7938677920028567,
      "status_mcpi": "Success",
      "len_raw_mcpi": 69,
      "len_feat_mcpi": 69,
      "time_sr": 0.5172753378283232,
      "status_sr": "Success",
      "len_raw_sr": 60,
      "len_feat_sr": 60
    },
    {
      "fold": 10,
      "instance_idx": 6,
      "prediction": 0,
      "len_binary_repr": 557,
      "len_theory": 29,
      "time_ext": 46.091437278082594,
      "status_ext": "Success",
      "len_raw_ext": 70,
      "len_feat_ext": 70,
      "time_cpi": 0.5718706499319524,
      "status_cpi": "Success",
      "len_raw_cpi": 81,
      "len_feat_cpi": 79,
      "time_mcpi": 0.8126926911063492,
      "status_mcpi": "Success",
      "len_raw_mcpi": 79,
      "len_feat_mcpi": 79,
      "time_sr": 0.5320940469391644,
      "status_sr": "Success",
      "len_raw_sr": 65,
      "len_feat_sr": 65
    },
    {
      "fold": 10,
      "instance_idx": 7,
      "prediction": 0,
      "len_binary_repr": 557,
      "len_theory": 29,
      "time_ext": 49.178506893105805,
      "status_ext": "Success",
      "len_raw_ext": 79,
      "len_feat_ext": 79,
      "time_cpi": 1.8505812659859657,
      "status_cpi": "Success",
      "len_raw_cpi": 82,
      "len_feat_cpi": 78,
      "time_mcpi": 2.3495885480660945,
      "status_mcpi": "Success",
      "len_raw_mcpi": 78,
      "len_feat_mcpi": 78,
      "time_sr": 0.8255776190198958,
      "status_sr": "Success",
      "len_raw_sr": 75,
      "len_feat_sr": 75
    },
    {
      "fold": 10,
      "instance_idx": 8,
      "prediction": 0,
      "len_binary_repr": 557,
      "len_theory": 29,
      "time_ext": 48.611259552882984,
      "status_ext": "Success",
      "len_raw_ext": 72,
      "len_feat_ext": 72,
      "time_cpi": 0.6051740569528192,
      "status_cpi": "Success",
      "len_raw_cpi": 78,
      "len_feat_cpi": 76,
      "time_mcpi": 0.8580989900510758,
      "status_mcpi": "Success",
      "len_raw_mcpi": 76,
      "len_feat_mcpi": 76,
      "time_sr": 0.4537086801137775,
      "status_sr": "Success",
      "len_raw_sr": 63,
      "len_feat_sr": 63
    },
    {
      "fold": 10,
      "instance_idx": 9,
      "prediction": 1,
      "len_binary_repr": 557,
      "len_theory": 29,
      "time_ext": 60.0017475259956,
      "status_ext": "Timeout",
      "len_raw_ext": null,
      "len_feat_ext": null,
      "time_cpi": 0.6786298139486462,
      "status_cpi": "Success",
      "len_raw_cpi": 88,
      "len_feat_cpi": 86,
      "time_mcpi": 0.8601608590688556,
      "status_mcpi": "Success",
      "len_raw_mcpi": 86,
      "len_feat_mcpi": 86,
      "time_sr": 0.32261661207303405,
      "status_sr": "Success",
      "len_raw_sr": 105,
      "len_feat_sr": 105
    },
    {
      "fold": 10,
      "instance_idx": 10,
      "prediction": 0,
      "len_binary_repr": 557,
      "len_theory": 29,
      "time_ext": 50.27329287910834,
      "status_ext": "Success",
      "len_raw_ext": 73,
      "len_feat_ext": 69,
      "time_cpi": 0.5628671611193568,
      "status_cpi": "Success",
      "len_raw_cpi": 77,
      "len_feat_cpi": 76,
      "time_mcpi": 0.9264482839498669,
      "status_mcpi": "Success",
      "len_raw_mcpi": 76,
      "len_feat_mcpi": 76,
      "time_sr": 0.38012856408022344,
      "status_sr": "Success",
      "len_raw_sr": 60,
      "len_feat_sr": 60
    }
  ]
}